{
"type": "FeatureCollection",
"name": "SOLIH_14",
"crs": { "type": "name", "properties": { "name": "urn:ogc:def:crs:OGC:1.3:CRS84" } },
"features": [
{ "type": "Feature", "properties": { "osm_id": 10873466286, "name": null, "amenity": null, "man_made": null, "leisure": "picnic_table", "playground": null, "memorial": null }, "geometry": { "type": "Point", "coordinates": [ -1.8369269, 52.3860984 ] } },
{ "type": "Feature", "properties": { "osm_id": 10873466287, "name": null, "amenity": null, "man_made": null, "leisure": "picnic_table", "playground": null, "memorial": null }, "geometry": { "type": "Point", "coordinates": [ -1.8370114, 52.3861073 ] } },
{ "type": "Feature", "properties": { "osm_id": 10873482110, "name": null, "amenity": "bench", "man_made": null, "leisure": null, "playground": null, "memorial": null }, "geometry": { "type": "Point", "coordinates": [ -1.8369065, 52.3861929 ] } },
{ "type": "Feature", "properties": { "osm_id": 10873404301, "name": null, "amenity": "bench", "man_made": null, "leisure": null, "playground": null, "memorial": null }, "geometry": { "type": "Point", "coordinates": [ -1.8359878, 52.3865419 ] } },
{ "type": "Feature", "properties": { "osm_id": 10873404303, "name": null, "amenity": "bench", "man_made": null, "leisure": null, "playground": null, "memorial": null }, "geometry": { "type": "Point", "coordinates": [ -1.8360628, 52.3866346 ] } },
{ "type": "Feature", "properties": { "osm_id": 10873482107, "name": null, "amenity": "bench", "man_made": null, "leisure": null, "playground": null, "memorial": null }, "geometry": { "type": "Point", "coordinates": [ -1.8372871, 52.3868417 ] } },
{ "type": "Feature", "properties": { "osm_id": 10873482105, "name": null, "amenity": "bench", "man_made": null, "leisure": null, "playground": null, "memorial": null }, "geometry": { "type": "Point", "coordinates": [ -1.8370771, 52.3869275 ] } }
]
}
