{
"type": "FeatureCollection",
"name": "TELWR_43_toilets",
"crs": { "type": "name", "properties": { "name": "urn:ogc:def:crs:OGC:1.3:CRS84" } },
"features": [
{ "type": "Feature", "properties": { "name": "Hadley Learning Community Waterloo Road", "payment_info": "Cost unknown", "accessible": "False", "radar": "Unknown", "women": "True", "men": "True", "baby_change": "True", "Mon": "Unknown", "Tue": "Unknown", "Wed": "Unknown", "Thu": "Unknown", "Fri": "Unknown", "Sat": "Unknown", "Sun": "Unknown", "index_right": 116, "park_offical_id": "TELWR_43" }, "geometry": { "type": "Point", "coordinates": [ -2.48591365, 52.70153866 ] } }
]
}
