{
"type": "FeatureCollection",
"name": "TELWR_73_toilets",
"crs": { "type": "name", "properties": { "name": "urn:ogc:def:crs:OGC:1.3:CRS84" } },
"features": [
{ "type": "Feature", "properties": { "name": "Unknown", "payment_info": "Free", "accessible": "False", "radar": "True", "women": "True", "men": "True", "baby_change": "Unknown", "Mon": "08:00-18:00", "Tue": "08:00-18:00", "Wed": "08:00-18:00", "Thu": "08:00-18:00", "Fri": "08:00-18:00", "Sat": "08:00-18:00", "Sun": "08:00-18:00", "index_right": 149, "park_offical_id": "TELWR_73" }, "geometry": { "type": "Point", "coordinates": [ -2.4599894, 52.6831249 ] } },
{ "type": "Feature", "properties": { "name": "Telford town center  by MS", "payment_info": "Free", "accessible": "True", "radar": "Unknown", "women": "True", "men": "True", "baby_change": "True", "Mon": "Unknown", "Tue": "Unknown", "Wed": "Unknown", "Thu": "Unknown", "Fri": "Unknown", "Sat": "Unknown", "Sun": "Unknown", "index_right": 149, "park_offical_id": "TELWR_73" }, "geometry": { "type": "Point", "coordinates": [ -2.447687509, 52.677351995 ] } }
]
}
