{
"type": "FeatureCollection",
"name": "99f4308b7411_visibility",
"crs": { "type": "name", "properties": { "name": "urn:ogc:def:crs:OGC:1.3:CRS84" } },
"features": [
{ "type": "Feature", "properties": { "visible_points": 0, "total_points": 51, "visibility_pct": 0.0 }, "geometry": { "type": "Point", "coordinates": [ -2.055166443294342, 52.443334719210036 ] } },
{ "type": "Feature", "properties": { "visible_points": 3, "total_points": 48, "visibility_pct": 6.25 }, "geometry": { "type": "Point", "coordinates": [ -2.054962585623118, 52.443334814804224 ] } },
{ "type": "Feature", "properties": { "visible_points": 0, "total_points": 43, "visibility_pct": 0.0 }, "geometry": { "type": "Point", "coordinates": [ -2.05475872795077, 52.443334910047007 ] } },
{ "type": "Feature", "properties": { "visible_points": 1, "total_points": 57, "visibility_pct": 1.7543859649122806 }, "geometry": { "type": "Point", "coordinates": [ -2.055472366857009, 52.443442457210168 ] } },
{ "type": "Feature", "properties": { "visible_points": 4, "total_points": 56, "visibility_pct": 7.1428571428571423 }, "geometry": { "type": "Point", "coordinates": [ -2.055268508690136, 52.443442553331678 ] } },
{ "type": "Feature", "properties": { "visible_points": 4, "total_points": 55, "visibility_pct": 7.2727272727272725 }, "geometry": { "type": "Point", "coordinates": [ -2.055064650522136, 52.44344264910179 ] } },
{ "type": "Feature", "properties": { "visible_points": 1, "total_points": 51, "visibility_pct": 1.9607843137254901 }, "geometry": { "type": "Point", "coordinates": [ -2.054860792353018, 52.44344274452051 ] } },
{ "type": "Feature", "properties": { "visible_points": 0, "total_points": 56, "visibility_pct": 0.0 }, "geometry": { "type": "Point", "coordinates": [ -2.055778291909979, 52.44355019441695 ] } },
{ "type": "Feature", "properties": { "visible_points": 4, "total_points": 61, "visibility_pct": 6.557377049180328 }, "geometry": { "type": "Point", "coordinates": [ -2.055574433247462, 52.443550291065812 ] } },
{ "type": "Feature", "properties": { "visible_points": 4, "total_points": 61, "visibility_pct": 6.557377049180328 }, "geometry": { "type": "Point", "coordinates": [ -2.055370574583817, 52.443550387363267 ] } },
{ "type": "Feature", "properties": { "visible_points": 3, "total_points": 60, "visibility_pct": 5.0 }, "geometry": { "type": "Point", "coordinates": [ -2.05516671591904, 52.443550483309323 ] } },
{ "type": "Feature", "properties": { "visible_points": 0, "total_points": 58, "visibility_pct": 0.0 }, "geometry": { "type": "Point", "coordinates": [ -2.054962857253142, 52.443550578903967 ] } },
{ "type": "Feature", "properties": { "visible_points": 5, "total_points": 58, "visibility_pct": 8.6206896551724146 }, "geometry": { "type": "Point", "coordinates": [ -2.055676500135811, 52.443658124831373 ] } },
{ "type": "Feature", "properties": { "visible_points": 1, "total_points": 61, "visibility_pct": 1.639344262295082 }, "geometry": { "type": "Point", "coordinates": [ -2.055472640975392, 52.44365822130478 ] } },
{ "type": "Feature", "properties": { "visible_points": 0, "total_points": 61, "visibility_pct": 0.0 }, "geometry": { "type": "Point", "coordinates": [ -2.055268781813834, 52.443658317426795 ] } },
{ "type": "Feature", "properties": { "visible_points": 0, "total_points": 52, "visibility_pct": 0.0 }, "geometry": { "type": "Point", "coordinates": [ -2.055778567522056, 52.443765958506894 ] } },
{ "type": "Feature", "properties": { "visible_points": 1, "total_points": 57, "visibility_pct": 1.7543859649122806 }, "geometry": { "type": "Point", "coordinates": [ -2.055574707864861, 52.443766055156225 ] } },
{ "type": "Feature", "properties": { "visible_points": 2, "total_points": 51, "visibility_pct": 3.9215686274509802 }, "geometry": { "type": "Point", "coordinates": [ -2.055676775252225, 52.443873888917636 ] } },
{ "type": "Feature", "properties": { "visible_points": 0, "total_points": 55, "visibility_pct": 0.0 }, "geometry": { "type": "Point", "coordinates": [ -2.055472915097114, 52.443873985391512 ] } },
{ "type": "Feature", "properties": { "visible_points": 0, "total_points": 48, "visibility_pct": 0.0 }, "geometry": { "type": "Point", "coordinates": [ -2.0555749824856, 52.443981819238772 ] } },
{ "type": "Feature", "properties": { "visible_points": 0, "total_points": 51, "visibility_pct": 0.0 }, "geometry": { "type": "Point", "coordinates": [ -2.055371121832567, 52.443981915537194 ] } },
{ "type": "Feature", "properties": { "visible_points": 3, "total_points": 43, "visibility_pct": 6.9767441860465116 }, "geometry": { "type": "Point", "coordinates": [ -2.055473189222177, 52.444089749470365 ] } },
{ "type": "Feature", "properties": { "visible_points": 2, "total_points": 44, "visibility_pct": 4.5454545454545459 }, "geometry": { "type": "Point", "coordinates": [ -2.055269328071227, 52.444089845593318 ] } }
]
}
