{
"type": "FeatureCollection",
"name": "SANDW_37_toilets",
"crs": { "type": "name", "properties": { "name": "urn:ogc:def:crs:OGC:1.3:CRS84" } },
"features": [
{ "type": "Feature", "properties": { "name": "145 High Street Rowley Regis", "payment_info": "Free", "accessible": "False", "radar": "True", "women": "True", "men": "True", "baby_change": "True", "Mon": "Unknown", "Tue": "Unknown", "Wed": "Unknown", "Thu": "Unknown", "Fri": "Unknown", "Sat": "Unknown", "Sun": "Unknown", "index_right": 1081, "park_offical_id": "SANDW_37" }, "geometry": { "type": "Point", "coordinates": [ -2.0422913, 52.4758131 ] } },
{ "type": "Feature", "properties": { "name": "Unknown", "payment_info": "Free", "accessible": "False", "radar": "Unknown", "women": "Unknown", "men": "Unknown", "baby_change": "Unknown", "Mon": "Unknown", "Tue": "Unknown", "Wed": "Unknown", "Thu": "Unknown", "Fri": "Unknown", "Sat": "Unknown", "Sun": "Unknown", "index_right": 1081, "park_offical_id": "SANDW_37" }, "geometry": { "type": "Point", "coordinates": [ -2.0396157, 52.47627258 ] } },
{ "type": "Feature", "properties": { "name": "Unknown", "payment_info": "Cost unknown", "accessible": "False", "radar": "Unknown", "women": "True", "men": "True", "baby_change": "True", "Mon": "07:30-17:00", "Tue": "07:30-17:00", "Wed": "07:30-17:00", "Thu": "07:30-17:00", "Fri": "07:30-17:00", "Sat": "07:30-17:00", "Sun": "Closed", "index_right": 1081, "park_offical_id": "SANDW_37" }, "geometry": { "type": "Point", "coordinates": [ -2.0385568, 52.4756545 ] } }
]
}
