{
"type": "FeatureCollection",
"name": "SANDW_1489_toilets",
"crs": { "type": "name", "properties": { "name": "urn:ogc:def:crs:OGC:1.3:CRS84" } },
"features": [
{ "type": "Feature", "properties": { "name": "Walsall Road  Jervoise Lane Stone Cross", "payment_info": "Free", "accessible": "False", "radar": "Unknown", "women": "Unknown", "men": "Unknown", "baby_change": "False", "Mon": "00:00-00:00", "Tue": "00:00-00:00", "Wed": "00:00-00:00", "Thu": "00:00-00:00", "Fri": "00:00-00:00", "Sat": "00:00-00:00", "Sun": "00:00-00:00", "index_right": 235, "park_offical_id": "SANDW_1489" }, "geometry": { "type": "Point", "coordinates": [ -1.983418465, 52.544476977 ] } },
{ "type": "Feature", "properties": { "name": "Beverley Road Stone Cross", "payment_info": "Cost unknown", "accessible": "False", "radar": "True", "women": "True", "men": "True", "baby_change": "True", "Mon": "09:30-17:30", "Tue": "09:30-17:30", "Wed": "09:30-17:30", "Thu": "09:30-17:30", "Fri": "09:30-17:30", "Sat": "09:30-17:30", "Sun": "09:30-17:30", "index_right": 235, "park_offical_id": "SANDW_1489" }, "geometry": { "type": "Point", "coordinates": [ -1.985963237, 52.544179827 ] } }
]
}
