{
"type": "FeatureCollection",
"name": "SANDW_1314_toilets",
"crs": { "type": "name", "properties": { "name": "urn:ogc:def:crs:OGC:1.3:CRS84" } },
"features": [
{ "type": "Feature", "properties": { "name": "Esso ", "payment_info": "Free", "accessible": "Unknown", "radar": "Unknown", "women": "True", "men": "True", "baby_change": "Unknown", "Mon": "Unknown", "Tue": "Unknown", "Wed": "Unknown", "Thu": "Unknown", "Fri": "Unknown", "Sat": "Unknown", "Sun": "Unknown", "index_right": 139, "park_offical_id": "SANDW_1314" }, "geometry": { "type": "Point", "coordinates": [ -2.053032517, 52.52129361 ] } }
]
}
