{
"type": "FeatureCollection",
"name": "SANDW_897_toilets",
"crs": { "type": "name", "properties": { "name": "urn:ogc:def:crs:OGC:1.3:CRS84" } },
"features": [
{ "type": "Feature", "properties": { "name": "Tipton Library", "payment_info": "Cost unknown", "accessible": "False", "radar": "False", "women": "True", "men": "True", "baby_change": "True", "Mon": "Unknown", "Tue": "Unknown", "Wed": "Unknown", "Thu": "Unknown", "Fri": "Unknown", "Sat": "Unknown", "Sun": "Unknown", "index_right": 1193, "park_offical_id": "SANDW_897" }, "geometry": { "type": "Point", "coordinates": [ -2.031633181, 52.527868777 ] } },
{ "type": "Feature", "properties": { "name": "Tipton Train Station", "payment_info": "Train Ticket Needed", "accessible": "Unknown", "radar": "Unknown", "women": "True", "men": "True", "baby_change": "Unknown", "Mon": "Unknown", "Tue": "Unknown", "Wed": "Unknown", "Thu": "Unknown", "Fri": "Unknown", "Sat": "Unknown", "Sun": "Unknown", "index_right": 1193, "park_offical_id": "SANDW_897" }, "geometry": { "type": "Point", "coordinates": [ -2.050103545, 52.524746928 ] } }
]
}
