{
"type": "FeatureCollection",
"name": "LICHF_63",
"crs": { "type": "name", "properties": { "name": "urn:ogc:def:crs:OGC:1.3:CRS84" } },
"features": [
{ "type": "Feature", "properties": { "osm_id": 3162678199, "name": null, "amenity": "bench", "man_made": null, "leisure": null, "playground": null, "memorial": null }, "geometry": { "type": "Point", "coordinates": [ -1.7640438, 52.6776398 ] } },
{ "type": "Feature", "properties": { "osm_id": 3162678201, "name": null, "amenity": null, "man_made": null, "leisure": "picnic_table", "playground": null, "memorial": null }, "geometry": { "type": "Point", "coordinates": [ -1.7645183, 52.6776576 ] } },
{ "type": "Feature", "properties": { "osm_id": 3162678200, "name": null, "amenity": "bench", "man_made": null, "leisure": null, "playground": null, "memorial": null }, "geometry": { "type": "Point", "coordinates": [ -1.7643397, 52.6776863 ] } }
]
}
