{
"type": "FeatureCollection",
"name": "1de40f0d5c54_visibility",
"crs": { "type": "name", "properties": { "name": "urn:ogc:def:crs:OGC:1.3:CRS84" } },
"features": [
{ "type": "Feature", "properties": { "visible_points": 0, "total_points": 51, "visibility_pct": 0.0 }, "geometry": { "type": "Point", "coordinates": [ -1.497333586761185, 52.434752683174864 ] } },
{ "type": "Feature", "properties": { "visible_points": 0, "total_points": 46, "visibility_pct": 0.0 }, "geometry": { "type": "Point", "coordinates": [ -1.497129780618206, 52.43475182131953 ] } },
{ "type": "Feature", "properties": { "visible_points": 0, "total_points": 58, "visibility_pct": 0.0 }, "geometry": { "type": "Point", "coordinates": [ -1.497638066337388, 52.434861848086726 ] } },
{ "type": "Feature", "properties": { "visible_points": 0, "total_points": 58, "visibility_pct": 0.0 }, "geometry": { "type": "Point", "coordinates": [ -1.497434259698594, 52.434860986754416 ] } },
{ "type": "Feature", "properties": { "visible_points": 4, "total_points": 54, "visibility_pct": 7.4074074074074066 }, "geometry": { "type": "Point", "coordinates": [ -1.497230453069903, 52.434860125070877 ] } },
{ "type": "Feature", "properties": { "visible_points": 0, "total_points": 48, "visibility_pct": 0.0 }, "geometry": { "type": "Point", "coordinates": [ -1.497026646451343, 52.434859263036103 ] } },
{ "type": "Feature", "properties": { "visible_points": 0, "total_points": 58, "visibility_pct": 0.0 }, "geometry": { "type": "Point", "coordinates": [ -1.497738740236083, 52.434970151408528 ] } },
{ "type": "Feature", "properties": { "visible_points": 6, "total_points": 58, "visibility_pct": 10.344827586206897 }, "geometry": { "type": "Point", "coordinates": [ -1.497534933111582, 52.434969290248006 ] } },
{ "type": "Feature", "properties": { "visible_points": 7, "total_points": 58, "visibility_pct": 12.068965517241379 }, "geometry": { "type": "Point", "coordinates": [ -1.497331125997192, 52.434968428736241 ] } },
{ "type": "Feature", "properties": { "visible_points": 8, "total_points": 54, "visibility_pct": 14.814814814814813 }, "geometry": { "type": "Point", "coordinates": [ -1.497127318892915, 52.43496756687324 ] } },
{ "type": "Feature", "properties": { "visible_points": 0, "total_points": 51, "visibility_pct": 0.0 }, "geometry": { "type": "Point", "coordinates": [ -1.498043222230695, 52.435079315281897 ] } },
{ "type": "Feature", "properties": { "visible_points": 7, "total_points": 56, "visibility_pct": 12.5 }, "geometry": { "type": "Point", "coordinates": [ -1.497839414610376, 52.435078454644369 ] } },
{ "type": "Feature", "properties": { "visible_points": 9, "total_points": 58, "visibility_pct": 15.517241379310345 }, "geometry": { "type": "Point", "coordinates": [ -1.497635607000166, 52.43507759365562 ] } },
{ "type": "Feature", "properties": { "visible_points": 8, "total_points": 58, "visibility_pct": 13.793103448275861 }, "geometry": { "type": "Point", "coordinates": [ -1.497431799400066, 52.435076732315636 ] } },
{ "type": "Feature", "properties": { "visible_points": 8, "total_points": 58, "visibility_pct": 13.793103448275861 }, "geometry": { "type": "Point", "coordinates": [ -1.49722799181008, 52.435075870624409 ] } },
{ "type": "Feature", "properties": { "visible_points": 0, "total_points": 53, "visibility_pct": 0.0 }, "geometry": { "type": "Point", "coordinates": [ -1.497024184230218, 52.435075008581968 ] } },
{ "type": "Feature", "properties": { "visible_points": 0, "total_points": 51, "visibility_pct": 0.0 }, "geometry": { "type": "Point", "coordinates": [ -1.497940089460265, 52.435186757794249 ] } },
{ "type": "Feature", "properties": { "visible_points": 9, "total_points": 55, "visibility_pct": 16.363636363636363 }, "geometry": { "type": "Point", "coordinates": [ -1.497736281364343, 52.435185896977266 ] } },
{ "type": "Feature", "properties": { "visible_points": 8, "total_points": 57, "visibility_pct": 14.035087719298245 }, "geometry": { "type": "Point", "coordinates": [ -1.49753247327853, 52.435185035809063 ] } },
{ "type": "Feature", "properties": { "visible_points": 0, "total_points": 58, "visibility_pct": 0.0 }, "geometry": { "type": "Point", "coordinates": [ -1.497328665202836, 52.435184174289631 ] } },
{ "type": "Feature", "properties": { "visible_points": 0, "total_points": 50, "visibility_pct": 0.0 }, "geometry": { "type": "Point", "coordinates": [ -1.497836956204121, 52.435294200212944 ] } },
{ "type": "Feature", "properties": { "visible_points": 3, "total_points": 53, "visibility_pct": 5.6603773584905666 }, "geometry": { "type": "Point", "coordinates": [ -1.497633147632598, 52.435293339216514 ] } },
{ "type": "Feature", "properties": { "visible_points": 0, "total_points": 47, "visibility_pct": 0.0 }, "geometry": { "type": "Point", "coordinates": [ -1.497733822462264, 52.435401642538018 ] } }
]
}
