{
"type": "FeatureCollection",
"name": "4802e6a8ab79_visibility",
"crs": { "type": "name", "properties": { "name": "urn:ogc:def:crs:OGC:1.3:CRS84" } },
"features": [
{ "type": "Feature", "properties": { "visible_points": 0, "total_points": 43, "visibility_pct": 0.0 }, "geometry": { "type": "Point", "coordinates": [ -1.46925808291713, 52.403697486869156 ] } },
{ "type": "Feature", "properties": { "visible_points": 6, "total_points": 49, "visibility_pct": 12.244897959183673 }, "geometry": { "type": "Point", "coordinates": [ -1.469054421425885, 52.403696576983208 ] } },
{ "type": "Feature", "properties": { "visible_points": 8, "total_points": 55, "visibility_pct": 14.545454545454545 }, "geometry": { "type": "Point", "coordinates": [ -1.468850759945597, 52.403695666746401 ] } },
{ "type": "Feature", "properties": { "visible_points": 6, "total_points": 57, "visibility_pct": 10.526315789473683 }, "geometry": { "type": "Point", "coordinates": [ -1.468647098476268, 52.403694756158735 ] } },
{ "type": "Feature", "properties": { "visible_points": 6, "total_points": 57, "visibility_pct": 10.526315789473683 }, "geometry": { "type": "Point", "coordinates": [ -1.468443437017906, 52.403693845220239 ] } },
{ "type": "Feature", "properties": { "visible_points": 0, "total_points": 54, "visibility_pct": 0.0 }, "geometry": { "type": "Point", "coordinates": [ -1.468239775569866, 52.403692933930991 ] } },
{ "type": "Feature", "properties": { "visible_points": 0, "total_points": 47, "visibility_pct": 0.0 }, "geometry": { "type": "Point", "coordinates": [ -1.468036114114148, 52.403692022296205 ] } },
{ "type": "Feature", "properties": { "visible_points": 0, "total_points": 40, "visibility_pct": 0.0 }, "geometry": { "type": "Point", "coordinates": [ -1.467832452652014, 52.403691110315187 ] } },
{ "type": "Feature", "properties": { "visible_points": 7, "total_points": 46, "visibility_pct": 15.217391304347828 }, "geometry": { "type": "Point", "coordinates": [ -1.469154961029191, 52.403804909594214 ] } },
{ "type": "Feature", "properties": { "visible_points": 9, "total_points": 52, "visibility_pct": 17.307692307692307 }, "geometry": { "type": "Point", "coordinates": [ -1.468951299045314, 52.403803999528776 ] } },
{ "type": "Feature", "properties": { "visible_points": 9, "total_points": 57, "visibility_pct": 15.789473684210526 }, "geometry": { "type": "Point", "coordinates": [ -1.468747637072394, 52.403803089112486 ] } },
{ "type": "Feature", "properties": { "visible_points": 6, "total_points": 57, "visibility_pct": 10.526315789473683 }, "geometry": { "type": "Point", "coordinates": [ -1.468543975110435, 52.403802178345344 ] } },
{ "type": "Feature", "properties": { "visible_points": 3, "total_points": 57, "visibility_pct": 5.2631578947368416 }, "geometry": { "type": "Point", "coordinates": [ -1.468340313159454, 52.403801267227372 ] } },
{ "type": "Feature", "properties": { "visible_points": 0, "total_points": 51, "visibility_pct": 0.0 }, "geometry": { "type": "Point", "coordinates": [ -1.468136651209681, 52.403800355760268 ] } },
{ "type": "Feature", "properties": { "visible_points": 2, "total_points": 44, "visibility_pct": 4.5454545454545459 }, "geometry": { "type": "Point", "coordinates": [ -1.467932989249378, 52.403799443950959 ] } },
{ "type": "Feature", "properties": { "visible_points": 9, "total_points": 48, "visibility_pct": 18.75 }, "geometry": { "type": "Point", "coordinates": [ -1.469051838637643, 52.403912332225495 ] } },
{ "type": "Feature", "properties": { "visible_points": 10, "total_points": 53, "visibility_pct": 18.867924528301888 }, "geometry": { "type": "Point", "coordinates": [ -1.468848176161129, 52.403911421980567 ] } },
{ "type": "Feature", "properties": { "visible_points": 7, "total_points": 57, "visibility_pct": 12.280701754385964 }, "geometry": { "type": "Point", "coordinates": [ -1.468644513695582, 52.403910511384801 ] } },
{ "type": "Feature", "properties": { "visible_points": 6, "total_points": 57, "visibility_pct": 10.526315789473683 }, "geometry": { "type": "Point", "coordinates": [ -1.468440851240993, 52.40390960043819 ] } },
{ "type": "Feature", "properties": { "visible_points": 6, "total_points": 49, "visibility_pct": 12.244897959183673 }, "geometry": { "type": "Point", "coordinates": [ -1.468948715742485, 52.404019754762999 ] } },
{ "type": "Feature", "properties": { "visible_points": 9, "total_points": 54, "visibility_pct": 16.666666666666664 }, "geometry": { "type": "Point", "coordinates": [ -1.468745052773331, 52.404018844338594 ] } }
]
}
