{
"type": "FeatureCollection",
"name": "a57485701be5_visibility",
"crs": { "type": "name", "properties": { "name": "urn:ogc:def:crs:OGC:1.3:CRS84" } },
"features": [
{ "type": "Feature", "properties": { "visible_points": 0, "total_points": 49, "visibility_pct": 0.0 }, "geometry": { "type": "Point", "coordinates": [ -1.56241698492019, 52.433754258522598 ] } },
{ "type": "Feature", "properties": { "visible_points": 0, "total_points": 52, "visibility_pct": 0.0 }, "geometry": { "type": "Point", "coordinates": [ -1.562213180004883, 52.433753506822939 ] } },
{ "type": "Feature", "properties": { "visible_points": 6, "total_points": 53, "visibility_pct": 11.320754716981133 }, "geometry": { "type": "Point", "coordinates": [ -1.562009375098785, 52.433752754772001 ] } },
{ "type": "Feature", "properties": { "visible_points": 4, "total_points": 50, "visibility_pct": 8.0 }, "geometry": { "type": "Point", "coordinates": [ -1.562517822229322, 52.433862511605859 ] } },
{ "type": "Feature", "properties": { "visible_points": 6, "total_points": 53, "visibility_pct": 11.320754716981133 }, "geometry": { "type": "Point", "coordinates": [ -1.562314016795957, 52.433861760081506 ] } },
{ "type": "Feature", "properties": { "visible_points": 7, "total_points": 53, "visibility_pct": 13.20754716981132 }, "geometry": { "type": "Point", "coordinates": [ -1.562110211371804, 52.433861008205874 ] } },
{ "type": "Feature", "properties": { "visible_points": 7, "total_points": 53, "visibility_pct": 13.20754716981132 }, "geometry": { "type": "Point", "coordinates": [ -1.561906405956876, 52.433860255978963 ] } },
{ "type": "Feature", "properties": { "visible_points": 4, "total_points": 53, "visibility_pct": 7.5471698113207548 }, "geometry": { "type": "Point", "coordinates": [ -1.562414854152181, 52.433970013240256 ] } },
{ "type": "Feature", "properties": { "visible_points": 10, "total_points": 53, "visibility_pct": 18.867924528301888 }, "geometry": { "type": "Point", "coordinates": [ -1.562211048212465, 52.433969261539453 ] } },
{ "type": "Feature", "properties": { "visible_points": 9, "total_points": 53, "visibility_pct": 16.981132075471699 }, "geometry": { "type": "Point", "coordinates": [ -1.562007242281969, 52.433968509487379 ] } },
{ "type": "Feature", "properties": { "visible_points": 12, "total_points": 53, "visibility_pct": 22.641509433962266 }, "geometry": { "type": "Point", "coordinates": [ -1.561803436360702, 52.433967757084041 ] } },
{ "type": "Feature", "properties": { "visible_points": 6, "total_points": 53, "visibility_pct": 11.320754716981133 }, "geometry": { "type": "Point", "coordinates": [ -1.562311885559456, 52.434077514784043 ] } },
{ "type": "Feature", "properties": { "visible_points": 9, "total_points": 53, "visibility_pct": 16.981132075471699 }, "geometry": { "type": "Point", "coordinates": [ -1.562108079113391, 52.434076762906813 ] } },
{ "type": "Feature", "properties": { "visible_points": 10, "total_points": 53, "visibility_pct": 18.867924528301888 }, "geometry": { "type": "Point", "coordinates": [ -1.561904272676553, 52.434076010678297 ] } },
{ "type": "Feature", "properties": { "visible_points": 8, "total_points": 52, "visibility_pct": 15.384615384615385 }, "geometry": { "type": "Point", "coordinates": [ -1.561700466248942, 52.434075258098503 ] } },
{ "type": "Feature", "properties": { "visible_points": 6, "total_points": 53, "visibility_pct": 11.320754716981133 }, "geometry": { "type": "Point", "coordinates": [ -1.562208916451143, 52.434185016237258 ] } },
{ "type": "Feature", "properties": { "visible_points": 4, "total_points": 53, "visibility_pct": 7.5471698113207548 }, "geometry": { "type": "Point", "coordinates": [ -1.562005109498734, 52.434184264183578 ] } },
{ "type": "Feature", "properties": { "visible_points": 5, "total_points": 51, "visibility_pct": 9.8039215686274517 }, "geometry": { "type": "Point", "coordinates": [ -1.561801302555546, 52.434183511778627 ] } },
{ "type": "Feature", "properties": { "visible_points": 8, "total_points": 46, "visibility_pct": 17.391304347826086 }, "geometry": { "type": "Point", "coordinates": [ -1.561597495621589, 52.434182759022384 ] } },
{ "type": "Feature", "properties": { "visible_points": 3, "total_points": 48, "visibility_pct": 6.25 }, "geometry": { "type": "Point", "coordinates": [ -1.561902139368479, 52.434291765369771 ] } },
{ "type": "Feature", "properties": { "visible_points": 4, "total_points": 44, "visibility_pct": 9.0909090909090917 }, "geometry": { "type": "Point", "coordinates": [ -1.561698331918945, 52.434291012788364 ] } }
]
}
