{
"type": "FeatureCollection",
"name": "db3242709064_visibility",
"crs": { "type": "name", "properties": { "name": "urn:ogc:def:crs:OGC:1.3:CRS84" } },
"features": [
{ "type": "Feature", "properties": { "visible_points": 5, "total_points": 47, "visibility_pct": 10.638297872340425 }, "geometry": { "type": "Point", "coordinates": [ -1.492969674435477, 52.417072953345553 ] } },
{ "type": "Feature", "properties": { "visible_points": 2, "total_points": 52, "visibility_pct": 3.8461538461538463 }, "geometry": { "type": "Point", "coordinates": [ -1.492765950143334, 52.417072084228856 ] } },
{ "type": "Feature", "properties": { "visible_points": 0, "total_points": 54, "visibility_pct": 0.0 }, "geometry": { "type": "Point", "coordinates": [ -1.492562225861721, 52.417071214761116 ] } },
{ "type": "Feature", "properties": { "visible_points": 4, "total_points": 46, "visibility_pct": 8.695652173913043 }, "geometry": { "type": "Point", "coordinates": [ -1.493070306162881, 52.417181264899575 ] } },
{ "type": "Feature", "properties": { "visible_points": 2, "total_points": 51, "visibility_pct": 3.9215686274509802 }, "geometry": { "type": "Point", "coordinates": [ -1.492866581351906, 52.417180395959171 ] } },
{ "type": "Feature", "properties": { "visible_points": 1, "total_points": 54, "visibility_pct": 1.8518518518518516 }, "geometry": { "type": "Point", "coordinates": [ -1.492662856551394, 52.417179526667731 ] } },
{ "type": "Feature", "properties": { "visible_points": 0, "total_points": 54, "visibility_pct": 0.0 }, "geometry": { "type": "Point", "coordinates": [ -1.49245913176135, 52.417178657025254 ] } },
{ "type": "Feature", "properties": { "visible_points": 0, "total_points": 53, "visibility_pct": 0.0 }, "geometry": { "type": "Point", "coordinates": [ -1.492255406981787, 52.417177787031733 ] } },
{ "type": "Feature", "properties": { "visible_points": 0, "total_points": 46, "visibility_pct": 0.0 }, "geometry": { "type": "Point", "coordinates": [ -1.492051682212694, 52.417176916687154 ] } },
{ "type": "Feature", "properties": { "visible_points": 1, "total_points": 49, "visibility_pct": 2.0408163265306123 }, "geometry": { "type": "Point", "coordinates": [ -1.492967213609328, 52.417288707391471 ] } },
{ "type": "Feature", "properties": { "visible_points": 1, "total_points": 54, "visibility_pct": 1.8518518518518516 }, "geometry": { "type": "Point", "coordinates": [ -1.492763488304921, 52.417287838273069 ] } },
{ "type": "Feature", "properties": { "visible_points": 1, "total_points": 54, "visibility_pct": 1.8518518518518516 }, "geometry": { "type": "Point", "coordinates": [ -1.492559763010988, 52.417286968803609 ] } },
{ "type": "Feature", "properties": { "visible_points": 2, "total_points": 54, "visibility_pct": 3.7037037037037033 }, "geometry": { "type": "Point", "coordinates": [ -1.492356037727521, 52.417286098983119 ] } },
{ "type": "Feature", "properties": { "visible_points": 2, "total_points": 49, "visibility_pct": 4.0816326530612246 }, "geometry": { "type": "Point", "coordinates": [ -1.492152312454528, 52.417285228811558 ] } },
{ "type": "Feature", "properties": { "visible_points": 0, "total_points": 42, "visibility_pct": 0.0 }, "geometry": { "type": "Point", "coordinates": [ -1.491948587192021, 52.417284358288981 ] } },
{ "type": "Feature", "properties": { "visible_points": 0, "total_points": 35, "visibility_pct": 0.0 }, "geometry": { "type": "Point", "coordinates": [ -1.491744861939993, 52.417283487415368 ] } },
{ "type": "Feature", "properties": { "visible_points": 12, "total_points": 46, "visibility_pct": 26.086956521739129 }, "geometry": { "type": "Point", "coordinates": [ -1.493067846360158, 52.417397018736523 ] } },
{ "type": "Feature", "properties": { "visible_points": 8, "total_points": 51, "visibility_pct": 15.686274509803921 }, "geometry": { "type": "Point", "coordinates": [ -1.492864120551855, 52.417396149791145 ] } },
{ "type": "Feature", "properties": { "visible_points": 8, "total_points": 54, "visibility_pct": 14.814814814814813 }, "geometry": { "type": "Point", "coordinates": [ -1.492660394754022, 52.417395280494716 ] } },
{ "type": "Feature", "properties": { "visible_points": 9, "total_points": 54, "visibility_pct": 16.666666666666664 }, "geometry": { "type": "Point", "coordinates": [ -1.492456668966653, 52.417394410847251 ] } },
{ "type": "Feature", "properties": { "visible_points": 8, "total_points": 51, "visibility_pct": 15.686274509803921 }, "geometry": { "type": "Point", "coordinates": [ -1.49225294318976, 52.417393540848735 ] } },
{ "type": "Feature", "properties": { "visible_points": 7, "total_points": 44, "visibility_pct": 15.909090909090908 }, "geometry": { "type": "Point", "coordinates": [ -1.492049217423346, 52.41739267049919 ] } }
]
}
