{
"type": "FeatureCollection",
"name": "SHROP_54",
"crs": { "type": "name", "properties": { "name": "urn:ogc:def:crs:OGC:1.3:CRS84" } },
"features": [
{ "type": "Feature", "properties": { "osm_id": 13432586375, "name": null, "amenity": "bench", "man_made": null, "leisure": null, "playground": null, "memorial": null }, "geometry": { "type": "Point", "coordinates": [ -2.6903278, 52.9691678 ] } },
{ "type": "Feature", "properties": { "osm_id": 12488588274, "name": null, "amenity": "bench", "man_made": null, "leisure": null, "playground": null, "memorial": null }, "geometry": { "type": "Point", "coordinates": [ -2.6872958, 52.9691722 ] } },
{ "type": "Feature", "properties": { "osm_id": 12488588275, "name": null, "amenity": "bench", "man_made": null, "leisure": null, "playground": null, "memorial": null }, "geometry": { "type": "Point", "coordinates": [ -2.6875225, 52.9692392 ] } },
{ "type": "Feature", "properties": { "osm_id": 12488588250, "name": null, "amenity": null, "man_made": null, "leisure": "picnic_table", "playground": null, "memorial": null }, "geometry": { "type": "Point", "coordinates": [ -2.6876217, 52.9692683 ] } },
{ "type": "Feature", "properties": { "osm_id": 12488588273, "name": null, "amenity": "bench", "man_made": null, "leisure": null, "playground": null, "memorial": null }, "geometry": { "type": "Point", "coordinates": [ -2.6874688, 52.9692828 ] } }
]
}
