{
"type": "FeatureCollection",
"name": "SHROP_1156",
"crs": { "type": "name", "properties": { "name": "urn:ogc:def:crs:OGC:1.3:CRS84" } },
"features": [
{ "type": "Feature", "properties": { "osm_id": 6829286406, "name": null, "amenity": "bench", "man_made": null, "leisure": null, "playground": null, "memorial": null }, "geometry": { "type": "Point", "coordinates": [ -2.8356623, 52.4390821 ] } },
{ "type": "Feature", "properties": { "osm_id": 6829286408, "name": null, "amenity": "bench", "man_made": null, "leisure": null, "playground": null, "memorial": null }, "geometry": { "type": "Point", "coordinates": [ -2.8357614, 52.4391304 ] } },
{ "type": "Feature", "properties": { "osm_id": 6834005161, "name": null, "amenity": "bench", "man_made": null, "leisure": null, "playground": null, "memorial": null }, "geometry": { "type": "Point", "coordinates": [ -2.8360944, 52.4392298 ] } },
{ "type": "Feature", "properties": { "osm_id": 6829286407, "name": null, "amenity": "bench", "man_made": null, "leisure": null, "playground": null, "memorial": null }, "geometry": { "type": "Point", "coordinates": [ -2.83618, 52.4392926 ] } }
]
}
