{
"type": "FeatureCollection",
"name": "SHROP_1270",
"crs": { "type": "name", "properties": { "name": "urn:ogc:def:crs:OGC:1.3:CRS84" } },
"features": [
{ "type": "Feature", "properties": { "osm_id": 4396031397, "name": null, "amenity": "bench", "man_made": null, "leisure": null, "playground": null, "memorial": null }, "geometry": { "type": "Point", "coordinates": [ -2.7506795, 52.7103307 ] } },
{ "type": "Feature", "properties": { "osm_id": 4396031400, "name": null, "amenity": "bench", "man_made": null, "leisure": null, "playground": null, "memorial": null }, "geometry": { "type": "Point", "coordinates": [ -2.7507884, 52.7103481 ] } },
{ "type": "Feature", "properties": { "osm_id": 4396031401, "name": null, "amenity": "bench", "man_made": null, "leisure": null, "playground": null, "memorial": null }, "geometry": { "type": "Point", "coordinates": [ -2.7507575, 52.7103538 ] } },
{ "type": "Feature", "properties": { "osm_id": 4396031402, "name": null, "amenity": "bench", "man_made": null, "leisure": null, "playground": null, "memorial": null }, "geometry": { "type": "Point", "coordinates": [ -2.7507924, 52.7103635 ] } }
]
}
