{
"type": "FeatureCollection",
"name": "MALHI_53_toilets",
"crs": { "type": "name", "properties": { "name": "urn:ogc:def:crs:OGC:1.3:CRS84" } },
"features": [
{ "type": "Feature", "properties": { "name": "Great Malvern Station", "payment_info": "Free", "accessible": "True", "radar": "Unknown", "women": "Unknown", "men": "Unknown", "baby_change": "False", "Mon": "Unknown", "Tue": "Unknown", "Wed": "Unknown", "Thu": "Unknown", "Fri": "Unknown", "Sat": "Unknown", "Sun": "Unknown", "index_right": 73, "park_offical_id": "MALHI_53" }, "geometry": { "type": "Point", "coordinates": [ -2.318281662, 52.10920685 ] } }
]
}
