{
"type": "FeatureCollection",
"name": "NORWA_6",
"crs": { "type": "name", "properties": { "name": "urn:ogc:def:crs:OGC:1.3:CRS84" } },
"features": [
{ "type": "Feature", "properties": { "osm_id": 10180486606, "name": null, "amenity": "bench", "man_made": null, "leisure": null, "playground": null, "memorial": null }, "geometry": { "type": "Point", "coordinates": [ -1.7029038, 52.5749922 ] } },
{ "type": "Feature", "properties": { "osm_id": 10180474553, "name": null, "amenity": "bench", "man_made": null, "leisure": null, "playground": null, "memorial": null }, "geometry": { "type": "Point", "coordinates": [ -1.7027254, 52.5750079 ] } },
{ "type": "Feature", "properties": { "osm_id": 10180385496, "name": null, "amenity": "bench", "man_made": null, "leisure": null, "playground": null, "memorial": null }, "geometry": { "type": "Point", "coordinates": [ -1.7030756, 52.5750153 ] } },
{ "type": "Feature", "properties": { "osm_id": 687697619, "name": null, "amenity": "bench", "man_made": null, "leisure": null, "playground": null, "memorial": null }, "geometry": { "type": "Point", "coordinates": [ -1.6951998, 52.5561177 ] } },
{ "type": "Feature", "properties": { "osm_id": 687697621, "name": null, "amenity": "bench", "man_made": null, "leisure": null, "playground": null, "memorial": null }, "geometry": { "type": "Point", "coordinates": [ -1.6970283, 52.5579766 ] } },
{ "type": "Feature", "properties": { "osm_id": 12114447067, "name": null, "amenity": "bench", "man_made": null, "leisure": null, "playground": null, "memorial": null }, "geometry": { "type": "Point", "coordinates": [ -1.6870669, 52.5612286 ] } },
{ "type": "Feature", "properties": { "osm_id": 11198896905, "name": null, "amenity": "bench", "man_made": null, "leisure": null, "playground": null, "memorial": null }, "geometry": { "type": "Point", "coordinates": [ -1.6983914, 52.5613166 ] } },
{ "type": "Feature", "properties": { "osm_id": 12465477814, "name": null, "amenity": "bench", "man_made": null, "leisure": null, "playground": null, "memorial": null }, "geometry": { "type": "Point", "coordinates": [ -1.6943869, 52.5619657 ] } },
{ "type": "Feature", "properties": { "osm_id": 12465480027, "name": null, "amenity": "bench", "man_made": null, "leisure": null, "playground": null, "memorial": null }, "geometry": { "type": "Point", "coordinates": [ -1.6959484, 52.5619789 ] } },
{ "type": "Feature", "properties": { "osm_id": 12465477817, "name": null, "amenity": "bench", "man_made": null, "leisure": null, "playground": null, "memorial": null }, "geometry": { "type": "Point", "coordinates": [ -1.6943611, 52.5620673 ] } },
{ "type": "Feature", "properties": { "osm_id": 12114421356, "name": null, "amenity": "bench", "man_made": null, "leisure": null, "playground": null, "memorial": null }, "geometry": { "type": "Point", "coordinates": [ -1.6873007, 52.5620836 ] } },
{ "type": "Feature", "properties": { "osm_id": 12465477819, "name": null, "amenity": "bench", "man_made": null, "leisure": null, "playground": null, "memorial": null }, "geometry": { "type": "Point", "coordinates": [ -1.6904517, 52.5623435 ] } },
{ "type": "Feature", "properties": { "osm_id": 12465477812, "name": null, "amenity": "bench", "man_made": null, "leisure": null, "playground": null, "memorial": null }, "geometry": { "type": "Point", "coordinates": [ -1.6903565, 52.5623487 ] } },
{ "type": "Feature", "properties": { "osm_id": 12114471627, "name": null, "amenity": "bench", "man_made": null, "leisure": null, "playground": null, "memorial": null }, "geometry": { "type": "Point", "coordinates": [ -1.6873309, 52.5625456 ] } },
{ "type": "Feature", "properties": { "osm_id": 11198896903, "name": null, "amenity": "bench", "man_made": null, "leisure": null, "playground": null, "memorial": null }, "geometry": { "type": "Point", "coordinates": [ -1.6973918, 52.5645836 ] } },
{ "type": "Feature", "properties": { "osm_id": 10180598821, "name": null, "amenity": "bench", "man_made": null, "leisure": null, "playground": null, "memorial": null }, "geometry": { "type": "Point", "coordinates": [ -1.6929644, 52.566689 ] } },
{ "type": "Feature", "properties": { "osm_id": 10180477610, "name": null, "amenity": "bench", "man_made": null, "leisure": null, "playground": null, "memorial": null }, "geometry": { "type": "Point", "coordinates": [ -1.7014849, 52.5747173 ] } },
{ "type": "Feature", "properties": { "osm_id": 10180525562, "name": null, "amenity": "bench", "man_made": null, "leisure": null, "playground": null, "memorial": null }, "geometry": { "type": "Point", "coordinates": [ -1.701891, 52.5751507 ] } }
]
}
