{
"type": "FeatureCollection",
"name": "4f75e4d777fd_visibility",
"crs": { "type": "name", "properties": { "name": "urn:ogc:def:crs:OGC:1.3:CRS84" } },
"features": [
{ "type": "Feature", "properties": { "visible_points": 5, "total_points": 52, "visibility_pct": 9.6153846153846168 }, "geometry": { "type": "Point", "coordinates": [ -1.707967958297961, 52.193766945570886 ] } },
{ "type": "Feature", "properties": { "visible_points": 0, "total_points": 52, "visibility_pct": 0.0 }, "geometry": { "type": "Point", "coordinates": [ -1.707765240241421, 52.193766445875276 ] } },
{ "type": "Feature", "properties": { "visible_points": 4, "total_points": 52, "visibility_pct": 7.6923076923076925 }, "geometry": { "type": "Point", "coordinates": [ -1.708068619238406, 52.1938750782545 ] } },
{ "type": "Feature", "properties": { "visible_points": 1, "total_points": 52, "visibility_pct": 1.9230769230769231 }, "geometry": { "type": "Point", "coordinates": [ -1.707865900660351, 52.193874578732945 ] } },
{ "type": "Feature", "properties": { "visible_points": 0, "total_points": 52, "visibility_pct": 0.0 }, "geometry": { "type": "Point", "coordinates": [ -1.707663182088485, 52.193874078863089 ] } },
{ "type": "Feature", "properties": { "visible_points": 0, "total_points": 52, "visibility_pct": 0.0 }, "geometry": { "type": "Point", "coordinates": [ -1.707460463522815, 52.193873578644997 ] } },
{ "type": "Feature", "properties": { "visible_points": 5, "total_points": 48, "visibility_pct": 10.416666666666668 }, "geometry": { "type": "Point", "coordinates": [ -1.708371999799905, 52.193983709848467 ] } },
{ "type": "Feature", "properties": { "visible_points": 0, "total_points": 52, "visibility_pct": 0.0 }, "geometry": { "type": "Point", "coordinates": [ -1.708169280694142, 52.193983210849197 ] } },
{ "type": "Feature", "properties": { "visible_points": 1, "total_points": 52, "visibility_pct": 1.9230769230769231 }, "geometry": { "type": "Point", "coordinates": [ -1.707966561594573, 52.193982711501668 ] } },
{ "type": "Feature", "properties": { "visible_points": 2, "total_points": 52, "visibility_pct": 3.8461538461538463 }, "geometry": { "type": "Point", "coordinates": [ -1.707763842501191, 52.193982211805853 ] } },
{ "type": "Feature", "properties": { "visible_points": 0, "total_points": 52, "visibility_pct": 0.0 }, "geometry": { "type": "Point", "coordinates": [ -1.707561123414005, 52.193981711761772 ] } },
{ "type": "Feature", "properties": { "visible_points": 1, "total_points": 51, "visibility_pct": 1.9607843137254901 }, "geometry": { "type": "Point", "coordinates": [ -1.707358404333011, 52.19398121136944 ] } },
{ "type": "Feature", "properties": { "visible_points": 0, "total_points": 51, "visibility_pct": 0.0 }, "geometry": { "type": "Point", "coordinates": [ -1.708269942665184, 52.194091343354941 ] } },
{ "type": "Feature", "properties": { "visible_points": 2, "total_points": 52, "visibility_pct": 3.8461538461538463 }, "geometry": { "type": "Point", "coordinates": [ -1.70806722304409, 52.194090844181439 ] } },
{ "type": "Feature", "properties": { "visible_points": 0, "total_points": 52, "visibility_pct": 0.0 }, "geometry": { "type": "Point", "coordinates": [ -1.707864503429192, 52.194090344659671 ] } },
{ "type": "Feature", "properties": { "visible_points": 1, "total_points": 52, "visibility_pct": 1.9230769230769231 }, "geometry": { "type": "Point", "coordinates": [ -1.707661783820484, 52.194089844789623 ] } },
{ "type": "Feature", "properties": { "visible_points": 0, "total_points": 52, "visibility_pct": 0.0 }, "geometry": { "type": "Point", "coordinates": [ -1.707459064217969, 52.194089344571317 ] } },
{ "type": "Feature", "properties": { "visible_points": 1, "total_points": 52, "visibility_pct": 1.9230769230769231 }, "geometry": { "type": "Point", "coordinates": [ -1.707965164872491, 52.194198477424571 ] } },
{ "type": "Feature", "properties": { "visible_points": 0, "total_points": 52, "visibility_pct": 0.0 }, "geometry": { "type": "Point", "coordinates": [ -1.707762444742259, 52.194197977728557 ] } },
{ "type": "Feature", "properties": { "visible_points": 2, "total_points": 52, "visibility_pct": 3.8461538461538463 }, "geometry": { "type": "Point", "coordinates": [ -1.707559724618224, 52.194197477684263 ] } },
{ "type": "Feature", "properties": { "visible_points": 2, "total_points": 50, "visibility_pct": 4.0 }, "geometry": { "type": "Point", "coordinates": [ -1.707863106179339, 52.194306110578538 ] } }
]
}
