{
"type": "FeatureCollection",
"name": "STOKE_4_toilets",
"crs": { "type": "name", "properties": { "name": "urn:ogc:def:crs:OGC:1.3:CRS84" } },
"features": [
{ "type": "Feature", "properties": { "name": "Longton Transport Lane", "payment_info": "Free", "accessible": "True", "radar": "False", "women": "True", "men": "True", "baby_change": "True", "Mon": "09:00-18:00", "Tue": "09:00-18:00", "Wed": "09:00-18:00", "Thu": "09:00-18:00", "Fri": "09:00-18:00", "Sat": "09:00-18:00", "Sun": "09:00-18:00", "index_right": 135, "park_offical_id": "STOKE_4" }, "geometry": { "type": "Point", "coordinates": [ -2.136379, 52.988595 ] } },
{ "type": "Feature", "properties": { "name": "Tesco Longton", "payment_info": "Free", "accessible": "False", "radar": "False", "women": "True", "men": "True", "baby_change": "True", "Mon": "09:00-17:00", "Tue": "09:00-17:00", "Wed": "09:00-17:00", "Thu": "09:00-17:00", "Fri": "09:00-17:00", "Sat": "09:00-17:00", "Sun": "09:00-17:00", "index_right": 135, "park_offical_id": "STOKE_4" }, "geometry": { "type": "Point", "coordinates": [ -2.139142156, 52.98952399 ] } }
]
}
