{
"type": "FeatureCollection",
"name": "075ffbbce3c0_visibility",
"crs": { "type": "name", "properties": { "name": "urn:ogc:def:crs:OGC:1.3:CRS84" } },
"features": [
{ "type": "Feature", "properties": { "visible_points": 3, "total_points": 46, "visibility_pct": 6.5217391304347823 }, "geometry": { "type": "Point", "coordinates": [ -2.016108823926885, 52.726912107085333 ] } },
{ "type": "Feature", "properties": { "visible_points": 0, "total_points": 40, "visibility_pct": 0.0 }, "geometry": { "type": "Point", "coordinates": [ -2.015903650384762, 52.726912136867242 ] } },
{ "type": "Feature", "properties": { "visible_points": 2, "total_points": 55, "visibility_pct": 3.6363636363636362 }, "geometry": { "type": "Point", "coordinates": [ -2.016621791479348, 52.727019905335155 ] } },
{ "type": "Feature", "properties": { "visible_points": 5, "total_points": 55, "visibility_pct": 9.0909090909090917 }, "geometry": { "type": "Point", "coordinates": [ -2.016416617411399, 52.727019936001767 ] } },
{ "type": "Feature", "properties": { "visible_points": 6, "total_points": 52, "visibility_pct": 11.538461538461538 }, "geometry": { "type": "Point", "coordinates": [ -2.016211443343144, 52.727019966313406 ] } },
{ "type": "Feature", "properties": { "visible_points": 0, "total_points": 46, "visibility_pct": 0.0 }, "geometry": { "type": "Point", "coordinates": [ -2.016006269274576, 52.727019996270037 ] } },
{ "type": "Feature", "properties": { "visible_points": 7, "total_points": 51, "visibility_pct": 13.725490196078432 }, "geometry": { "type": "Point", "coordinates": [ -2.016929587069279, 52.727127732929461 ] } },
{ "type": "Feature", "properties": { "visible_points": 8, "total_points": 54, "visibility_pct": 14.814814814814813 }, "geometry": { "type": "Point", "coordinates": [ -2.016724412475221, 52.727127764125797 ] } },
{ "type": "Feature", "properties": { "visible_points": 6, "total_points": 55, "visibility_pct": 10.909090909090908 }, "geometry": { "type": "Point", "coordinates": [ -2.01651923788084, 52.72712779496716 ] } },
{ "type": "Feature", "properties": { "visible_points": 5, "total_points": 55, "visibility_pct": 9.0909090909090917 }, "geometry": { "type": "Point", "coordinates": [ -2.016314063286146, 52.727127825453508 ] } },
{ "type": "Feature", "properties": { "visible_points": 0, "total_points": 51, "visibility_pct": 0.0 }, "geometry": { "type": "Point", "coordinates": [ -2.016108888691145, 52.727127855584875 ] } },
{ "type": "Feature", "properties": { "visible_points": 4, "total_points": 47, "visibility_pct": 8.5106382978723403 }, "geometry": { "type": "Point", "coordinates": [ -2.017032209118354, 52.727235591457429 ] } },
{ "type": "Feature", "properties": { "visible_points": 4, "total_points": 51, "visibility_pct": 7.8431372549019605 }, "geometry": { "type": "Point", "coordinates": [ -2.016827033997851, 52.727235622828495 ] } },
{ "type": "Feature", "properties": { "visible_points": 5, "total_points": 54, "visibility_pct": 9.2592592592592595 }, "geometry": { "type": "Point", "coordinates": [ -2.016621858877039, 52.727235653844588 ] } },
{ "type": "Feature", "properties": { "visible_points": 2, "total_points": 55, "visibility_pct": 3.6363636363636362 }, "geometry": { "type": "Point", "coordinates": [ -2.016416683755913, 52.727235684505686 ] } },
{ "type": "Feature", "properties": { "visible_points": 0, "total_points": 55, "visibility_pct": 0.0 }, "geometry": { "type": "Point", "coordinates": [ -2.016211508634463, 52.727235714811762 ] } },
{ "type": "Feature", "properties": { "visible_points": 3, "total_points": 47, "visibility_pct": 6.3829787234042552 }, "geometry": { "type": "Point", "coordinates": [ -2.016929656047253, 52.727343481443242 ] } },
{ "type": "Feature", "properties": { "visible_points": 4, "total_points": 50, "visibility_pct": 8.0 }, "geometry": { "type": "Point", "coordinates": [ -2.016724480399998, 52.727343512634071 ] } },
{ "type": "Feature", "properties": { "visible_points": 0, "total_points": 53, "visibility_pct": 0.0 }, "geometry": { "type": "Point", "coordinates": [ -2.016519304752431, 52.7273435434699 ] } },
{ "type": "Feature", "properties": { "visible_points": 1, "total_points": 42, "visibility_pct": 2.3809523809523809 }, "geometry": { "type": "Point", "coordinates": [ -2.017032278623421, 52.727451339970038 ] } },
{ "type": "Feature", "properties": { "visible_points": 2, "total_points": 46, "visibility_pct": 4.3478260869565215 }, "geometry": { "type": "Point", "coordinates": [ -2.016827102449728, 52.727451371335611 ] } },
{ "type": "Feature", "properties": { "visible_points": 0, "total_points": 49, "visibility_pct": 0.0 }, "geometry": { "type": "Point", "coordinates": [ -2.016621926275718, 52.727451402346155 ] } }
]
}
