{
"type": "FeatureCollection",
"name": "STAFF_33",
"crs": { "type": "name", "properties": { "name": "urn:ogc:def:crs:OGC:1.3:CRS84" } },
"features": [
{ "type": "Feature", "properties": { "osm_id": 5066730350, "name": null, "amenity": "bench", "man_made": null, "leisure": null, "playground": null, "memorial": null }, "geometry": { "type": "Point", "coordinates": [ -2.3697957, 52.7741218 ] } },
{ "type": "Feature", "properties": { "osm_id": 5044135359, "name": null, "amenity": null, "man_made": null, "leisure": "picnic_table", "playground": null, "memorial": null }, "geometry": { "type": "Point", "coordinates": [ -2.3693507, 52.7745652 ] } },
{ "type": "Feature", "properties": { "osm_id": 5044717598, "name": null, "amenity": null, "man_made": null, "leisure": "picnic_table", "playground": null, "memorial": null }, "geometry": { "type": "Point", "coordinates": [ -2.3693651, 52.7746712 ] } },
{ "type": "Feature", "properties": { "osm_id": 5060859081, "name": null, "amenity": "bench", "man_made": null, "leisure": null, "playground": null, "memorial": null }, "geometry": { "type": "Point", "coordinates": [ -2.3690303, 52.7753046 ] } },
{ "type": "Feature", "properties": { "osm_id": 5060859080, "name": null, "amenity": "bench", "man_made": null, "leisure": null, "playground": null, "memorial": null }, "geometry": { "type": "Point", "coordinates": [ -2.3691087, 52.7753602 ] } }
]
}
