{
"type": "FeatureCollection",
"name": "STAFF_56",
"crs": { "type": "name", "properties": { "name": "urn:ogc:def:crs:OGC:1.3:CRS84" } },
"features": [
{ "type": "Feature", "properties": { "osm_id": 8625290500, "name": null, "amenity": "bench", "man_made": null, "leisure": null, "playground": null, "memorial": null }, "geometry": { "type": "Point", "coordinates": [ -2.1158934, 52.8130656 ] } },
{ "type": "Feature", "properties": { "osm_id": 8625290501, "name": null, "amenity": "bench", "man_made": null, "leisure": null, "playground": null, "memorial": null }, "geometry": { "type": "Point", "coordinates": [ -2.1158599, 52.8130932 ] } },
{ "type": "Feature", "properties": { "osm_id": 8625290507, "name": null, "amenity": "bench", "man_made": null, "leisure": null, "playground": null, "memorial": null }, "geometry": { "type": "Point", "coordinates": [ -2.1154421, 52.813494 ] } },
{ "type": "Feature", "properties": { "osm_id": 8625290496, "name": null, "amenity": "bench", "man_made": null, "leisure": null, "playground": null, "memorial": null }, "geometry": { "type": "Point", "coordinates": [ -2.1158471, 52.8136043 ] } },
{ "type": "Feature", "properties": { "osm_id": 8625290497, "name": null, "amenity": "bench", "man_made": null, "leisure": null, "playground": null, "memorial": null }, "geometry": { "type": "Point", "coordinates": [ -2.1158257, 52.8136407 ] } }
]
}
