{
"type": "FeatureCollection",
"name": "STAFF_46",
"crs": { "type": "name", "properties": { "name": "urn:ogc:def:crs:OGC:1.3:CRS84" } },
"features": [
{ "type": "Feature", "properties": { "osm_id": 7917982220, "name": null, "amenity": null, "man_made": null, "leisure": "picnic_table", "playground": null, "memorial": null }, "geometry": { "type": "Point", "coordinates": [ -2.10601, 52.818 ] } },
{ "type": "Feature", "properties": { "osm_id": 8625290442, "name": null, "amenity": "bench", "man_made": null, "leisure": null, "playground": null, "memorial": null }, "geometry": { "type": "Point", "coordinates": [ -2.1065184, 52.8180314 ] } },
{ "type": "Feature", "properties": { "osm_id": 8625276105, "name": null, "amenity": null, "man_made": null, "leisure": "picnic_table", "playground": null, "memorial": null }, "geometry": { "type": "Point", "coordinates": [ -2.1060826, 52.8181497 ] } },
{ "type": "Feature", "properties": { "osm_id": 8625276102, "name": null, "amenity": null, "man_made": null, "leisure": "picnic_table", "playground": null, "memorial": null }, "geometry": { "type": "Point", "coordinates": [ -2.1062241, 52.8181716 ] } },
{ "type": "Feature", "properties": { "osm_id": 8625276103, "name": null, "amenity": null, "man_made": null, "leisure": "picnic_table", "playground": null, "memorial": null }, "geometry": { "type": "Point", "coordinates": [ -2.1059264, 52.8181761 ] } },
{ "type": "Feature", "properties": { "osm_id": 8625276104, "name": null, "amenity": null, "man_made": null, "leisure": "picnic_table", "playground": null, "memorial": null }, "geometry": { "type": "Point", "coordinates": [ -2.106037, 52.8181935 ] } },
{ "type": "Feature", "properties": { "osm_id": 7910116440, "name": null, "amenity": "bench", "man_made": null, "leisure": null, "playground": null, "memorial": null }, "geometry": { "type": "Point", "coordinates": [ -2.1062892, 52.8183761 ] } },
{ "type": "Feature", "properties": { "osm_id": 7909926303, "name": null, "amenity": "bench", "man_made": null, "leisure": null, "playground": null, "memorial": null }, "geometry": { "type": "Point", "coordinates": [ -2.1062402, 52.818406 ] } },
{ "type": "Feature", "properties": { "osm_id": 7910116439, "name": null, "amenity": "bench", "man_made": null, "leisure": null, "playground": null, "memorial": null }, "geometry": { "type": "Point", "coordinates": [ -2.1062543, 52.8184479 ] } },
{ "type": "Feature", "properties": { "osm_id": 7917949514, "name": null, "amenity": "bench", "man_made": null, "leisure": null, "playground": null, "memorial": null }, "geometry": { "type": "Point", "coordinates": [ -2.1085426, 52.81851 ] } },
{ "type": "Feature", "properties": { "osm_id": 7910116446, "name": null, "amenity": "bench", "man_made": null, "leisure": null, "playground": null, "memorial": null }, "geometry": { "type": "Point", "coordinates": [ -2.1053424, 52.8185353 ] } },
{ "type": "Feature", "properties": { "osm_id": 7909871983, "name": null, "amenity": "bench", "man_made": null, "leisure": null, "playground": null, "memorial": null }, "geometry": { "type": "Point", "coordinates": [ -2.1076887, 52.819067 ] } }
]
}
