{
"type": "FeatureCollection",
"name": "TELWR_21",
"crs": { "type": "name", "properties": { "name": "urn:ogc:def:crs:OGC:1.3:CRS84" } },
"features": [
{ "type": "Feature", "properties": { "osm_id": 11045293841, "name": null, "amenity": "bench", "man_made": null, "leisure": null, "playground": null, "memorial": null }, "geometry": { "type": "Point", "coordinates": [ -2.4990175, 52.7092557 ] } },
{ "type": "Feature", "properties": { "osm_id": 11139443727, "name": null, "amenity": "bench", "man_made": null, "leisure": null, "playground": null, "memorial": null }, "geometry": { "type": "Point", "coordinates": [ -2.4984107, 52.7097264 ] } }
]
}
