{
"type": "FeatureCollection",
"name": "e36aa09010d3_visibility",
"crs": { "type": "name", "properties": { "name": "urn:ogc:def:crs:OGC:1.3:CRS84" } },
"features": [
{ "type": "Feature", "properties": { "visible_points": 5, "total_points": 42, "visibility_pct": 11.904761904761903 }, "geometry": { "type": "Point", "coordinates": [ -1.238561647278182, 52.397922347976198 ] } },
{ "type": "Feature", "properties": { "visible_points": 6, "total_points": 45, "visibility_pct": 13.333333333333334 }, "geometry": { "type": "Point", "coordinates": [ -1.238358020212151, 52.397921036587285 ] } },
{ "type": "Feature", "properties": { "visible_points": 6, "total_points": 50, "visibility_pct": 12.0 }, "geometry": { "type": "Point", "coordinates": [ -1.238457979501602, 52.398029565075035 ] } },
{ "type": "Feature", "properties": { "visible_points": 5, "total_points": 52, "visibility_pct": 9.6153846153846168 }, "geometry": { "type": "Point", "coordinates": [ -1.238254351940884, 52.398028253509693 ] } },
{ "type": "Feature", "properties": { "visible_points": 6, "total_points": 57, "visibility_pct": 10.526315789473683 }, "geometry": { "type": "Point", "coordinates": [ -1.23835431121449, 52.398136782083192 ] } },
{ "type": "Feature", "properties": { "visible_points": 4, "total_points": 57, "visibility_pct": 7.0175438596491224 }, "geometry": { "type": "Point", "coordinates": [ -1.238150683159082, 52.398135470341444 ] } },
{ "type": "Feature", "properties": { "visible_points": 0, "total_points": 56, "visibility_pct": 0.0 }, "geometry": { "type": "Point", "coordinates": [ -1.237947055119506, 52.398134158248844 ] } },
{ "type": "Feature", "properties": { "visible_points": 5, "total_points": 57, "visibility_pct": 8.7719298245614024 }, "geometry": { "type": "Point", "coordinates": [ -1.238454270982772, 52.398245310568043 ] } },
{ "type": "Feature", "properties": { "visible_points": 5, "total_points": 57, "visibility_pct": 8.7719298245614024 }, "geometry": { "type": "Point", "coordinates": [ -1.238250642416841, 52.398243999000712 ] } },
{ "type": "Feature", "properties": { "visible_points": 4, "total_points": 57, "visibility_pct": 7.0175438596491224 }, "geometry": { "type": "Point", "coordinates": [ -1.23804701386674, 52.398242687082551 ] } },
{ "type": "Feature", "properties": { "visible_points": 0, "total_points": 57, "visibility_pct": 0.0 }, "geometry": { "type": "Point", "coordinates": [ -1.237843385332476, 52.398241374813551 ] } },
{ "type": "Feature", "properties": { "visible_points": 5, "total_points": 57, "visibility_pct": 8.7719298245614024 }, "geometry": { "type": "Point", "coordinates": [ -1.238350602169279, 52.398352527571333 ] } },
{ "type": "Feature", "properties": { "visible_points": 7, "total_points": 57, "visibility_pct": 12.280701754385964 }, "geometry": { "type": "Point", "coordinates": [ -1.238146973108648, 52.398351215827581 ] } },
{ "type": "Feature", "properties": { "visible_points": 5, "total_points": 56, "visibility_pct": 8.9285714285714288 }, "geometry": { "type": "Point", "coordinates": [ -1.237943344063854, 52.398349903733013 ] } },
{ "type": "Feature", "properties": { "visible_points": 0, "total_points": 53, "visibility_pct": 0.0 }, "geometry": { "type": "Point", "coordinates": [ -1.237739715034897, 52.398348591287586 ] } },
{ "type": "Feature", "properties": { "visible_points": 6, "total_points": 54, "visibility_pct": 11.111111111111111 }, "geometry": { "type": "Point", "coordinates": [ -1.2384505624164, 52.398461056053264 ] } },
{ "type": "Feature", "properties": { "visible_points": 8, "total_points": 54, "visibility_pct": 14.814814814814813 }, "geometry": { "type": "Point", "coordinates": [ -1.23824693284524, 52.398459744483965 ] } },
{ "type": "Feature", "properties": { "visible_points": 8, "total_points": 53, "visibility_pct": 15.09433962264151 }, "geometry": { "type": "Point", "coordinates": [ -1.238043303289913, 52.398458432563807 ] } },
{ "type": "Feature", "properties": { "visible_points": 8, "total_points": 51, "visibility_pct": 15.686274509803921 }, "geometry": { "type": "Point", "coordinates": [ -1.237839673750421, 52.398457120292818 ] } },
{ "type": "Feature", "properties": { "visible_points": 6, "total_points": 50, "visibility_pct": 12.0 }, "geometry": { "type": "Point", "coordinates": [ -1.238346893076518, 52.398568273051673 ] } },
{ "type": "Feature", "properties": { "visible_points": 6, "total_points": 49, "visibility_pct": 12.244897959183673 }, "geometry": { "type": "Point", "coordinates": [ -1.238143263010653, 52.398566961305953 ] } },
{ "type": "Feature", "properties": { "visible_points": 8, "total_points": 48, "visibility_pct": 16.666666666666664 }, "geometry": { "type": "Point", "coordinates": [ -1.237939632960628, 52.398565649209395 ] } },
{ "type": "Feature", "properties": { "visible_points": 5, "total_points": 45, "visibility_pct": 11.111111111111111 }, "geometry": { "type": "Point", "coordinates": [ -1.238243223226084, 52.398675489959423 ] } }
]
}
