{
"type": "FeatureCollection",
"name": "COVEN_264",
"crs": { "type": "name", "properties": { "name": "urn:ogc:def:crs:OGC:1.3:CRS84" } },
"features": [
{ "type": "Feature", "properties": { "osm_id": 1680563655, "name": null, "amenity": "bench", "man_made": null, "leisure": null, "playground": null, "memorial": null }, "geometry": { "type": "Point", "coordinates": [ -1.5220709, 52.399335 ] } },
{ "type": "Feature", "properties": { "osm_id": 1680563671, "name": null, "amenity": "bench", "man_made": null, "leisure": null, "playground": null, "memorial": null }, "geometry": { "type": "Point", "coordinates": [ -1.5224262, 52.3994302 ] } },
{ "type": "Feature", "properties": { "osm_id": 1680563731, "name": null, "amenity": "bench", "man_made": null, "leisure": null, "playground": null, "memorial": null }, "geometry": { "type": "Point", "coordinates": [ -1.5221133, 52.3998393 ] } },
{ "type": "Feature", "properties": { "osm_id": 1680563741, "name": null, "amenity": "bench", "man_made": null, "leisure": null, "playground": null, "memorial": null }, "geometry": { "type": "Point", "coordinates": [ -1.5220679, 52.3998998 ] } }
]
}
