{
"type": "FeatureCollection",
"name": "9892b42375dc_visibility",
"crs": { "type": "name", "properties": { "name": "urn:ogc:def:crs:OGC:1.3:CRS84" } },
"features": [
{ "type": "Feature", "properties": { "visible_points": 9, "total_points": 46, "visibility_pct": 19.565217391304348 }, "geometry": { "type": "Point", "coordinates": [ -2.157584597448131, 52.727219010494267 ] } },
{ "type": "Feature", "properties": { "visible_points": 14, "total_points": 50, "visibility_pct": 28.000000000000004 }, "geometry": { "type": "Point", "coordinates": [ -2.15737942075426, 52.727219284608182 ] } },
{ "type": "Feature", "properties": { "visible_points": 14, "total_points": 52, "visibility_pct": 26.923076923076923 }, "geometry": { "type": "Point", "coordinates": [ -2.157174244057095, 52.727219558367125 ] } },
{ "type": "Feature", "properties": { "visible_points": 0, "total_points": 53, "visibility_pct": 0.0 }, "geometry": { "type": "Point", "coordinates": [ -2.156969067356641, 52.727219831771052 ] } },
{ "type": "Feature", "properties": { "visible_points": 17, "total_points": 51, "visibility_pct": 33.333333333333329 }, "geometry": { "type": "Point", "coordinates": [ -2.157482399697907, 52.727327021870742 ] } },
{ "type": "Feature", "properties": { "visible_points": 14, "total_points": 53, "visibility_pct": 26.415094339622641 }, "geometry": { "type": "Point", "coordinates": [ -2.157277222494749, 52.727327295809332 ] } },
{ "type": "Feature", "properties": { "visible_points": 12, "total_points": 53, "visibility_pct": 22.641509433962266 }, "geometry": { "type": "Point", "coordinates": [ -2.157072045288296, 52.727327569392941 ] } },
{ "type": "Feature", "properties": { "visible_points": 1, "total_points": 53, "visibility_pct": 1.8867924528301887 }, "geometry": { "type": "Point", "coordinates": [ -2.156866868078558, 52.727327842621555 ] } },
{ "type": "Feature", "properties": { "visible_points": 16, "total_points": 53, "visibility_pct": 30.188679245283019 }, "geometry": { "type": "Point", "coordinates": [ -2.15738020144167, 52.72743503315867 ] } },
{ "type": "Feature", "properties": { "visible_points": 14, "total_points": 53, "visibility_pct": 26.415094339622641 }, "geometry": { "type": "Point", "coordinates": [ -2.157175023729227, 52.727435306921926 ] } },
{ "type": "Feature", "properties": { "visible_points": 9, "total_points": 53, "visibility_pct": 16.981132075471699 }, "geometry": { "type": "Point", "coordinates": [ -2.156969846013486, 52.727435580330216 ] } },
{ "type": "Feature", "properties": { "visible_points": 6, "total_points": 53, "visibility_pct": 11.320754716981133 }, "geometry": { "type": "Point", "coordinates": [ -2.156764668294462, 52.72743585338349 ] } },
{ "type": "Feature", "properties": { "visible_points": 14, "total_points": 53, "visibility_pct": 26.415094339622641 }, "geometry": { "type": "Point", "coordinates": [ -2.157278002679427, 52.72754304435805 ] } },
{ "type": "Feature", "properties": { "visible_points": 9, "total_points": 53, "visibility_pct": 16.981132075471699 }, "geometry": { "type": "Point", "coordinates": [ -2.157072824457686, 52.727543317945987 ] } },
{ "type": "Feature", "properties": { "visible_points": 2, "total_points": 53, "visibility_pct": 3.7735849056603774 }, "geometry": { "type": "Point", "coordinates": [ -2.156867646232658, 52.727543591178929 ] } },
{ "type": "Feature", "properties": { "visible_points": 14, "total_points": 53, "visibility_pct": 26.415094339622641 }, "geometry": { "type": "Point", "coordinates": [ -2.157175803411163, 52.727651055468861 ] } },
{ "type": "Feature", "properties": { "visible_points": 11, "total_points": 52, "visibility_pct": 21.153846153846153 }, "geometry": { "type": "Point", "coordinates": [ -2.156970624680129, 52.727651328881471 ] } },
{ "type": "Feature", "properties": { "visible_points": 3, "total_points": 49, "visibility_pct": 6.1224489795918364 }, "geometry": { "type": "Point", "coordinates": [ -2.156765445945809, 52.727651601939087 ] } },
{ "type": "Feature", "properties": { "visible_points": 15, "total_points": 48, "visibility_pct": 31.25 }, "geometry": { "type": "Point", "coordinates": [ -2.15707360363688, 52.727759066491117 ] } },
{ "type": "Feature", "properties": { "visible_points": 7, "total_points": 46, "visibility_pct": 15.217391304347828 }, "geometry": { "type": "Point", "coordinates": [ -2.156868424396547, 52.727759339728401 ] } },
{ "type": "Feature", "properties": { "visible_points": 8, "total_points": 42, "visibility_pct": 19.047619047619047 }, "geometry": { "type": "Point", "coordinates": [ -2.156663245152937, 52.727759612610662 ] } }
]
}
