{
"type": "FeatureCollection",
"name": "WYRFO_28_toilets",
"crs": { "type": "name", "properties": { "name": "urn:ogc:def:crs:OGC:1.3:CRS84" } },
"features": [
{ "type": "Feature", "properties": { "name": "Brinton Park Four WindsSutton Road", "payment_info": "Cost unknown", "accessible": "False", "radar": "Unknown", "women": "True", "men": "True", "baby_change": "False", "Mon": "Unknown", "Tue": "Unknown", "Wed": "Unknown", "Thu": "Unknown", "Fri": "Unknown", "Sat": "Unknown", "Sun": "Unknown", "index_right": 73, "park_offical_id": "WYRFO_28" }, "geometry": { "type": "Point", "coordinates": [ -2.2615433, 52.3809204 ] } }
]
}
