{
"type": "FeatureCollection",
"name": "HEREF_50",
"crs": { "type": "name", "properties": { "name": "urn:ogc:def:crs:OGC:1.3:CRS84" } },
"features": [
{ "type": "Feature", "properties": { "osm_id": 13074167788, "name": null, "amenity": "bench", "man_made": null, "leisure": null, "playground": null, "memorial": null }, "geometry": { "type": "Point", "coordinates": [ -2.5887211, 51.9136208 ] } },
{ "type": "Feature", "properties": { "osm_id": 13074212696, "name": null, "amenity": "bench", "man_made": null, "leisure": null, "playground": null, "memorial": null }, "geometry": { "type": "Point", "coordinates": [ -2.5887617, 51.9136474 ] } }
]
}
