{
"type": "FeatureCollection",
"name": "HEREF_27",
"crs": { "type": "name", "properties": { "name": "urn:ogc:def:crs:OGC:1.3:CRS84" } },
"features": [
{ "type": "Feature", "properties": { "osm_id": 11644980375, "name": null, "amenity": null, "man_made": null, "leisure": "picnic_table", "playground": null, "memorial": null }, "geometry": { "type": "Point", "coordinates": [ -2.7276177, 52.0783762 ] } },
{ "type": "Feature", "properties": { "osm_id": 11644980376, "name": null, "amenity": null, "man_made": null, "leisure": "picnic_table", "playground": null, "memorial": null }, "geometry": { "type": "Point", "coordinates": [ -2.7275779, 52.0784001 ] } },
{ "type": "Feature", "properties": { "osm_id": 11644980377, "name": null, "amenity": null, "man_made": null, "leisure": "picnic_table", "playground": null, "memorial": null }, "geometry": { "type": "Point", "coordinates": [ -2.727539, 52.0784138 ] } }
]
}
