{
"type": "FeatureCollection",
"name": "HEREF_35",
"crs": { "type": "name", "properties": { "name": "urn:ogc:def:crs:OGC:1.3:CRS84" } },
"features": [
{ "type": "Feature", "properties": { "osm_id": 472388882, "name": null, "amenity": "bench", "man_made": null, "leisure": null, "playground": null, "memorial": null }, "geometry": { "type": "Point", "coordinates": [ -2.7677593, 52.2263175 ] } },
{ "type": "Feature", "properties": { "osm_id": 13730277376, "name": null, "amenity": null, "man_made": null, "leisure": "picnic_table", "playground": null, "memorial": null }, "geometry": { "type": "Point", "coordinates": [ -2.7665873, 52.2267552 ] } },
{ "type": "Feature", "properties": { "osm_id": 472388819, "name": null, "amenity": "bench", "man_made": null, "leisure": null, "playground": null, "memorial": null }, "geometry": { "type": "Point", "coordinates": [ -2.7662657, 52.2268093 ] } },
{ "type": "Feature", "properties": { "osm_id": 472388869, "name": null, "amenity": "bench", "man_made": null, "leisure": null, "playground": null, "memorial": null }, "geometry": { "type": "Point", "coordinates": [ -2.7641679, 52.2270859 ] } }
]
}
