{
"type": "FeatureCollection",
"name": "NORWA_49_toilets",
"crs": { "type": "name", "properties": { "name": "urn:ogc:def:crs:OGC:1.3:CRS84" } },
"features": [
{ "type": "Feature", "properties": { "name": "Atherstone Leisure Complex", "payment_info": "Free", "accessible": "True", "radar": "Unknown", "women": "True", "men": "True", "baby_change": "Unknown", "Mon": "07:00-21:30", "Tue": "07:00-21:30", "Wed": "07:00-21:30", "Thu": "07:00-21:30", "Fri": "07:00-21:30", "Sat": "08:00-16:00", "Sun": "09:00-14:00", "index_right": 26, "park_offical_id": "NORWA_49" }, "geometry": { "type": "Point", "coordinates": [ -1.549258915, 52.579034144 ] } }
]
}
