{
"type": "FeatureCollection",
"name": "RUGBY_31_toilets",
"crs": { "type": "name", "properties": { "name": "urn:ogc:def:crs:OGC:1.3:CRS84" } },
"features": [
{ "type": "Feature", "properties": { "name": "Newbold Quarry Disabled Toilet Avonmere Newbold Road", "payment_info": "Cost unknown", "accessible": "False", "radar": "Unknown", "women": "Unknown", "men": "Unknown", "baby_change": "False", "Mon": "Unknown", "Tue": "Unknown", "Wed": "Unknown", "Thu": "Unknown", "Fri": "Unknown", "Sat": "Unknown", "Sun": "Unknown", "index_right": 45, "park_offical_id": "RUGBY_31" }, "geometry": { "type": "Point", "coordinates": [ -1.277607011, 52.389701658 ] } }
]
}
