{
"type": "FeatureCollection",
"name": "RUGBY_27_toilets",
"crs": { "type": "name", "properties": { "name": "urn:ogc:def:crs:OGC:1.3:CRS84" } },
"features": [
{ "type": "Feature", "properties": { "name": "Art Gallery Museum and Library Little Elborow Street", "payment_info": "Free", "accessible": "False", "radar": "Unknown", "women": "True", "men": "True", "baby_change": "True", "Mon": "Unknown", "Tue": "Unknown", "Wed": "Unknown", "Thu": "Unknown", "Fri": "Unknown", "Sat": "Unknown", "Sun": "Unknown", "index_right": 40, "park_offical_id": "RUGBY_27" }, "geometry": { "type": "Point", "coordinates": [ -1.264446042, 52.371702594 ] } }
]
}
