{
"type": "FeatureCollection",
"name": "TAMWO_6_toilets",
"crs": { "type": "name", "properties": { "name": "urn:ogc:def:crs:OGC:1.3:CRS84" } },
"features": [
{ "type": "Feature", "properties": { "name": "Coop", "payment_info": "Free", "accessible": "True", "radar": "True", "women": "True", "men": "True", "baby_change": "True", "Mon": "Unknown", "Tue": "Unknown", "Wed": "Unknown", "Thu": "Unknown", "Fri": "Unknown", "Sat": "Unknown", "Sun": "Unknown", "index_right": 39, "park_offical_id": "TAMWO_6" }, "geometry": { "type": "Point", "coordinates": [ -1.683292687, 52.647294334 ] } }
]
}
