{
"type": "FeatureCollection",
"name": "9962f0e69b71_visibility",
"crs": { "type": "name", "properties": { "name": "urn:ogc:def:crs:OGC:1.3:CRS84" } },
"features": [
{ "type": "Feature", "properties": { "visible_points": 0, "total_points": 52, "visibility_pct": 0.0 }, "geometry": { "type": "Point", "coordinates": [ -2.023777378717547, 52.499881287615665 ] } },
{ "type": "Feature", "properties": { "visible_points": 4, "total_points": 56, "visibility_pct": 7.1428571428571423 }, "geometry": { "type": "Point", "coordinates": [ -2.023573263036512, 52.499881328842527 ] } },
{ "type": "Feature", "properties": { "visible_points": 4, "total_points": 58, "visibility_pct": 6.8965517241379306 }, "geometry": { "type": "Point", "coordinates": [ -2.023369147355007, 52.499881369717293 ] } },
{ "type": "Feature", "properties": { "visible_points": 0, "total_points": 52, "visibility_pct": 0.0 }, "geometry": { "type": "Point", "coordinates": [ -2.023879495806537, 52.499989146615391 ] } },
{ "type": "Feature", "properties": { "visible_points": 0, "total_points": 61, "visibility_pct": 0.0 }, "geometry": { "type": "Point", "coordinates": [ -2.023471263441218, 52.499989229072256 ] } },
{ "type": "Feature", "properties": { "visible_points": 0, "total_points": 62, "visibility_pct": 0.0 }, "geometry": { "type": "Point", "coordinates": [ -2.023267147257844, 52.49998926977252 ] } },
{ "type": "Feature", "properties": { "visible_points": 6, "total_points": 61, "visibility_pct": 9.8360655737704921 }, "geometry": { "type": "Point", "coordinates": [ -2.02306303107401, 52.499989310120668 ] } },
{ "type": "Feature", "properties": { "visible_points": 5, "total_points": 53, "visibility_pct": 9.433962264150944 }, "geometry": { "type": "Point", "coordinates": [ -2.02285891488971, 52.499989350116728 ] } },
{ "type": "Feature", "properties": { "visible_points": 0, "total_points": 50, "visibility_pct": 0.0 }, "geometry": { "type": "Point", "coordinates": [ -2.02398161339739, 52.500097005523507 ] } },
{ "type": "Feature", "properties": { "visible_points": 1, "total_points": 55, "visibility_pct": 1.8181818181818181 }, "geometry": { "type": "Point", "coordinates": [ -2.02377749671357, 52.500097047105619 ] } },
{ "type": "Feature", "properties": { "visible_points": 1, "total_points": 57, "visibility_pct": 1.7543859649122806 }, "geometry": { "type": "Point", "coordinates": [ -2.022961029973578, 52.50009720991298 ] } },
{ "type": "Feature", "properties": { "visible_points": 0, "total_points": 49, "visibility_pct": 0.0 }, "geometry": { "type": "Point", "coordinates": [ -2.022756913287421, 52.500097249734551 ] } },
{ "type": "Feature", "properties": { "visible_points": 6, "total_points": 41, "visibility_pct": 14.634146341463413 }, "geometry": { "type": "Point", "coordinates": [ -2.0225527966008, 52.500097289204 ] } },
{ "type": "Feature", "properties": { "visible_points": 3, "total_points": 36, "visibility_pct": 8.3333333333333321 }, "geometry": { "type": "Point", "coordinates": [ -2.02234867991373, 52.500097328321345 ] } },
{ "type": "Feature", "properties": { "visible_points": 0, "total_points": 46, "visibility_pct": 0.0 }, "geometry": { "type": "Point", "coordinates": [ -2.024083731490098, 52.50020486434007 ] } },
{ "type": "Feature", "properties": { "visible_points": 1, "total_points": 52, "visibility_pct": 1.9230769230769231 }, "geometry": { "type": "Point", "coordinates": [ -2.023879614304893, 52.500204906099817 ] } },
{ "type": "Feature", "properties": { "visible_points": 3, "total_points": 37, "visibility_pct": 8.1081081081081088 }, "geometry": { "type": "Point", "coordinates": [ -2.022450793995239, 52.50020518855888 ] } },
{ "type": "Feature", "properties": { "visible_points": 1, "total_points": 32, "visibility_pct": 3.125 }, "geometry": { "type": "Point", "coordinates": [ -2.022246676806305, 52.500205227501709 ] } },
{ "type": "Feature", "properties": { "visible_points": 0, "total_points": 40, "visibility_pct": 0.0 }, "geometry": { "type": "Point", "coordinates": [ -2.02418585008543, 52.500312723063445 ] } },
{ "type": "Feature", "properties": { "visible_points": 0, "total_points": 47, "visibility_pct": 0.0 }, "geometry": { "type": "Point", "coordinates": [ -2.023981732398829, 52.5003127650008 ] } },
{ "type": "Feature", "properties": { "visible_points": 0, "total_points": 38, "visibility_pct": 0.0 }, "geometry": { "type": "Point", "coordinates": [ -2.024083851165278, 52.500420623725894 ] } }
]
}
