{
"type": "FeatureCollection",
"name": "e187d3ec71fb_visibility",
"crs": { "type": "name", "properties": { "name": "urn:ogc:def:crs:OGC:1.3:CRS84" } },
"features": [
{ "type": "Feature", "properties": { "visible_points": 4, "total_points": 35, "visibility_pct": 11.428571428571429 }, "geometry": { "type": "Point", "coordinates": [ -2.032515009693154, 52.550057708296855 ] } },
{ "type": "Feature", "properties": { "visible_points": 4, "total_points": 39, "visibility_pct": 10.256410256410255 }, "geometry": { "type": "Point", "coordinates": [ -2.032310660864317, 52.55005776368359 ] } },
{ "type": "Feature", "properties": { "visible_points": 5, "total_points": 43, "visibility_pct": 11.627906976744185 }, "geometry": { "type": "Point", "coordinates": [ -2.032106312034796, 52.550057818717548 ] } },
{ "type": "Feature", "properties": { "visible_points": 0, "total_points": 32, "visibility_pct": 0.0 }, "geometry": { "type": "Point", "coordinates": [ -2.030471521374567, 52.550058246289673 ] } },
{ "type": "Feature", "properties": { "visible_points": 0, "total_points": 38, "visibility_pct": 0.0 }, "geometry": { "type": "Point", "coordinates": [ -2.032412917172668, 52.550165616210876 ] } },
{ "type": "Feature", "properties": { "visible_points": 0, "total_points": 42, "visibility_pct": 0.0 }, "geometry": { "type": "Point", "coordinates": [ -2.032208567818936, 52.550165671402866 ] } },
{ "type": "Feature", "properties": { "visible_points": 1, "total_points": 46, "visibility_pct": 2.1739130434782608 }, "geometry": { "type": "Point", "coordinates": [ -2.032004218464527, 52.550165726242078 ] } },
{ "type": "Feature", "properties": { "visible_points": 5, "total_points": 51, "visibility_pct": 9.8039215686274517 }, "geometry": { "type": "Point", "coordinates": [ -2.031799869109437, 52.550165780728527 ] } },
{ "type": "Feature", "properties": { "visible_points": 10, "total_points": 56, "visibility_pct": 17.857142857142858 }, "geometry": { "type": "Point", "coordinates": [ -2.031595519753678, 52.550165834862227 ] } },
{ "type": "Feature", "properties": { "visible_points": 10, "total_points": 57, "visibility_pct": 17.543859649122805 }, "geometry": { "type": "Point", "coordinates": [ -2.031391170397248, 52.55016588864315 ] } },
{ "type": "Feature", "properties": { "visible_points": 0, "total_points": 45, "visibility_pct": 0.0 }, "geometry": { "type": "Point", "coordinates": [ -2.030982471682409, 52.550165995146671 ] } },
{ "type": "Feature", "properties": { "visible_points": 0, "total_points": 40, "visibility_pct": 0.0 }, "geometry": { "type": "Point", "coordinates": [ -2.030778122324003, 52.55016604786929 ] } },
{ "type": "Feature", "properties": { "visible_points": 0, "total_points": 35, "visibility_pct": 0.0 }, "geometry": { "type": "Point", "coordinates": [ -2.030573772964949, 52.550166100239146 ] } },
{ "type": "Feature", "properties": { "visible_points": 0, "total_points": 48, "visibility_pct": 0.0 }, "geometry": { "type": "Point", "coordinates": [ -2.031902124370026, 52.550273633658101 ] } },
{ "type": "Feature", "properties": { "visible_points": 0, "total_points": 53, "visibility_pct": 0.0 }, "geometry": { "type": "Point", "coordinates": [ -2.031697774490045, 52.550273687949812 ] } },
{ "type": "Feature", "properties": { "visible_points": 0, "total_points": 54, "visibility_pct": 0.0 }, "geometry": { "type": "Point", "coordinates": [ -2.031493424609399, 52.550273741888745 ] } },
{ "type": "Feature", "properties": { "visible_points": 0, "total_points": 53, "visibility_pct": 0.0 }, "geometry": { "type": "Point", "coordinates": [ -2.031289074728082, 52.550273795474922 ] } },
{ "type": "Feature", "properties": { "visible_points": 0, "total_points": 47, "visibility_pct": 0.0 }, "geometry": { "type": "Point", "coordinates": [ -2.031084724846106, 52.550273848708329 ] } },
{ "type": "Feature", "properties": { "visible_points": 0, "total_points": 42, "visibility_pct": 0.0 }, "geometry": { "type": "Point", "coordinates": [ -2.030880374963476, 52.550273901588952 ] } },
{ "type": "Feature", "properties": { "visible_points": 0, "total_points": 37, "visibility_pct": 0.0 }, "geometry": { "type": "Point", "coordinates": [ -2.030676025080191, 52.550273954116825 ] } }
]
}
