{
"type": "FeatureCollection",
"name": "b73478ce8c8f_visibility",
"crs": { "type": "name", "properties": { "name": "urn:ogc:def:crs:OGC:1.3:CRS84" } },
"features": [
{ "type": "Feature", "properties": { "visible_points": 0, "total_points": 51, "visibility_pct": 0.0 }, "geometry": { "type": "Point", "coordinates": [ -2.140971109067941, 52.793111615673276 ] } },
{ "type": "Feature", "properties": { "visible_points": 1, "total_points": 52, "visibility_pct": 1.9230769230769231 }, "geometry": { "type": "Point", "coordinates": [ -2.140765621252965, 52.793111861799467 ] } },
{ "type": "Feature", "properties": { "visible_points": 4, "total_points": 52, "visibility_pct": 7.6923076923076925 }, "geometry": { "type": "Point", "coordinates": [ -2.140560133435023, 52.793112107569797 ] } },
{ "type": "Feature", "properties": { "visible_points": 0, "total_points": 54, "visibility_pct": 0.0 }, "geometry": { "type": "Point", "coordinates": [ -2.141074203735001, 52.793219366181987 ] } },
{ "type": "Feature", "properties": { "visible_points": 0, "total_points": 55, "visibility_pct": 0.0 }, "geometry": { "type": "Point", "coordinates": [ -2.140868715411422, 52.793219612486773 ] } },
{ "type": "Feature", "properties": { "visible_points": 0, "total_points": 55, "visibility_pct": 0.0 }, "geometry": { "type": "Point", "coordinates": [ -2.140663227084892, 52.79321985843572 ] } },
{ "type": "Feature", "properties": { "visible_points": 4, "total_points": 55, "visibility_pct": 7.2727272727272725 }, "geometry": { "type": "Point", "coordinates": [ -2.140457738755402, 52.793220104028833 ] } },
{ "type": "Feature", "properties": { "visible_points": 5, "total_points": 53, "visibility_pct": 9.433962264150944 }, "geometry": { "type": "Point", "coordinates": [ -2.140252250422971, 52.7932203492661 ] } },
{ "type": "Feature", "properties": { "visible_points": 0, "total_points": 55, "visibility_pct": 0.0 }, "geometry": { "type": "Point", "coordinates": [ -2.141177298913592, 52.793327116599102 ] } },
{ "type": "Feature", "properties": { "visible_points": 0, "total_points": 55, "visibility_pct": 0.0 }, "geometry": { "type": "Point", "coordinates": [ -2.140971810081424, 52.79332736308249 ] } },
{ "type": "Feature", "properties": { "visible_points": 0, "total_points": 55, "visibility_pct": 0.0 }, "geometry": { "type": "Point", "coordinates": [ -2.140766321246295, 52.793327609210039 ] } },
{ "type": "Feature", "properties": { "visible_points": 1, "total_points": 55, "visibility_pct": 1.8181818181818181 }, "geometry": { "type": "Point", "coordinates": [ -2.140560832408211, 52.793327854981754 ] } },
{ "type": "Feature", "properties": { "visible_points": 3, "total_points": 55, "visibility_pct": 5.4545454545454541 }, "geometry": { "type": "Point", "coordinates": [ -2.140355343567175, 52.793328100397616 ] } },
{ "type": "Feature", "properties": { "visible_points": 2, "total_points": 55, "visibility_pct": 3.6363636363636362 }, "geometry": { "type": "Point", "coordinates": [ -2.141074905262966, 52.79343511358659 ] } },
{ "type": "Feature", "properties": { "visible_points": 0, "total_points": 55, "visibility_pct": 0.0 }, "geometry": { "type": "Point", "coordinates": [ -2.140869415919243, 52.793435359892733 ] } },
{ "type": "Feature", "properties": { "visible_points": 1, "total_points": 55, "visibility_pct": 1.8181818181818181 }, "geometry": { "type": "Point", "coordinates": [ -2.140663926572557, 52.793435605843044 ] } },
{ "type": "Feature", "properties": { "visible_points": 0, "total_points": 55, "visibility_pct": 0.0 }, "geometry": { "type": "Point", "coordinates": [ -2.140458437222919, 52.793435851437522 ] } },
{ "type": "Feature", "properties": { "visible_points": 2, "total_points": 55, "visibility_pct": 3.6363636363636362 }, "geometry": { "type": "Point", "coordinates": [ -2.14097251110373, 52.793543110483839 ] } },
{ "type": "Feature", "properties": { "visible_points": 0, "total_points": 55, "visibility_pct": 0.0 }, "geometry": { "type": "Point", "coordinates": [ -2.140767021248445, 52.793543356612744 ] } },
{ "type": "Feature", "properties": { "visible_points": 0, "total_points": 55, "visibility_pct": 0.0 }, "geometry": { "type": "Point", "coordinates": [ -2.140561531390203, 52.793543602385824 ] } },
{ "type": "Feature", "properties": { "visible_points": 1, "total_points": 51, "visibility_pct": 1.9607843137254901 }, "geometry": { "type": "Point", "coordinates": [ -2.140870116435882, 52.793651107290835 ] } },
{ "type": "Feature", "properties": { "visible_points": 0, "total_points": 51, "visibility_pct": 0.0 }, "geometry": { "type": "Point", "coordinates": [ -2.140664626069032, 52.793651353242517 ] } },
{ "type": "Feature", "properties": { "visible_points": 1, "total_points": 44, "visibility_pct": 2.2727272727272729 }, "geometry": { "type": "Point", "coordinates": [ -2.140767721259411, 52.793759104007592 ] } }
]
}
