{
"type": "FeatureCollection",
"name": "Redditch_street_lamps",
"crs": { "type": "name", "properties": { "name": "urn:ogc:def:crs:OGC:1.3:CRS84" } },
"features": [
{ "type": "Feature", "properties": { "element_type": "node", "osmid": 1616181643, "authority": "Redditch", "source": "osm", "year": null }, "geometry": { "type": "Point", "coordinates": [ -1.9410544, 52.3078955 ] } }
]
}
