{
"type": "FeatureCollection",
"name": "SANDW_1723",
"crs": { "type": "name", "properties": { "name": "urn:ogc:def:crs:OGC:1.3:CRS84" } },
"features": [
{ "type": "Feature", "properties": { "osm_id": 12342360508, "name": null, "amenity": "bench", "man_made": null, "leisure": null, "playground": null, "memorial": null }, "geometry": { "type": "Point", "coordinates": [ -2.0000441, 52.5124074 ] } },
{ "type": "Feature", "properties": { "osm_id": 12342360507, "name": null, "amenity": "bench", "man_made": null, "leisure": null, "playground": null, "memorial": null }, "geometry": { "type": "Point", "coordinates": [ -2.0001033, 52.5124568 ] } }
]
}
