{
"type": "FeatureCollection",
"name": "BIRMI_128",
"crs": { "type": "name", "properties": { "name": "urn:ogc:def:crs:OGC:1.3:CRS84" } },
"features": [
{ "type": "Feature", "properties": { "osm_id": 973614165, "name": null, "amenity": "bench", "man_made": null, "leisure": null, "playground": null, "memorial": null }, "geometry": { "type": "Point", "coordinates": [ -1.909933, 52.4801573 ] } },
{ "type": "Feature", "properties": { "osm_id": 973614170, "name": null, "amenity": "bench", "man_made": null, "leisure": null, "playground": null, "memorial": null }, "geometry": { "type": "Point", "coordinates": [ -1.9091642, 52.4802806 ] } },
{ "type": "Feature", "properties": { "osm_id": 973614166, "name": null, "amenity": "bench", "man_made": null, "leisure": null, "playground": null, "memorial": null }, "geometry": { "type": "Point", "coordinates": [ -1.9098135, 52.4803139 ] } },
{ "type": "Feature", "properties": { "osm_id": 973614163, "name": null, "amenity": "bench", "man_made": null, "leisure": null, "playground": null, "memorial": null }, "geometry": { "type": "Point", "coordinates": [ -1.9097564, 52.4803328 ] } },
{ "type": "Feature", "properties": { "osm_id": 973614169, "name": null, "amenity": "bench", "man_made": null, "leisure": null, "playground": null, "memorial": null }, "geometry": { "type": "Point", "coordinates": [ -1.909707, 52.4803534 ] } },
{ "type": "Feature", "properties": { "osm_id": 973614167, "name": null, "amenity": "bench", "man_made": null, "leisure": null, "playground": null, "memorial": null }, "geometry": { "type": "Point", "coordinates": [ -1.9096551, 52.4803676 ] } },
{ "type": "Feature", "properties": { "osm_id": 968582640, "name": null, "amenity": "bench", "man_made": null, "leisure": null, "playground": null, "memorial": null }, "geometry": { "type": "Point", "coordinates": [ -1.9091308, 52.4804666 ] } },
{ "type": "Feature", "properties": { "osm_id": 968582642, "name": null, "amenity": "bench", "man_made": null, "leisure": null, "playground": null, "memorial": null }, "geometry": { "type": "Point", "coordinates": [ -1.9091018, 52.4804784 ] } },
{ "type": "Feature", "properties": { "osm_id": 968582641, "name": null, "amenity": "bench", "man_made": null, "leisure": null, "playground": null, "memorial": null }, "geometry": { "type": "Point", "coordinates": [ -1.9090728, 52.4804902 ] } },
{ "type": "Feature", "properties": { "osm_id": 968582639, "name": null, "amenity": "bench", "man_made": null, "leisure": null, "playground": null, "memorial": null }, "geometry": { "type": "Point", "coordinates": [ -1.9090438, 52.480502 ] } }
]
}
