{
"type": "FeatureCollection",
"name": "BIRMI_8",
"crs": { "type": "name", "properties": { "name": "urn:ogc:def:crs:OGC:1.3:CRS84" } },
"features": [
{ "type": "Feature", "properties": { "osm_id": 4868152802, "name": null, "amenity": "bench", "man_made": null, "leisure": null, "playground": null, "memorial": null }, "geometry": { "type": "Point", "coordinates": [ -1.8589335, 52.5528669 ] } },
{ "type": "Feature", "properties": { "osm_id": 4868152803, "name": null, "amenity": "bench", "man_made": null, "leisure": null, "playground": null, "memorial": null }, "geometry": { "type": "Point", "coordinates": [ -1.8594659, 52.553177 ] } },
{ "type": "Feature", "properties": { "osm_id": 2499899187, "name": null, "amenity": "bench", "man_made": null, "leisure": null, "playground": null, "memorial": null }, "geometry": { "type": "Point", "coordinates": [ -1.8603327, 52.5532391 ] } }
]
}
