{
"type": "FeatureCollection",
"name": "BIRMI_74",
"crs": { "type": "name", "properties": { "name": "urn:ogc:def:crs:OGC:1.3:CRS84" } },
"features": [
{ "type": "Feature", "properties": { "osm_id": 8520993817, "name": null, "amenity": "bench", "man_made": null, "leisure": null, "playground": null, "memorial": null }, "geometry": { "type": "Point", "coordinates": [ -1.8686353, 52.5307624 ] } },
{ "type": "Feature", "properties": { "osm_id": 8520993717, "name": null, "amenity": "bench", "man_made": null, "leisure": null, "playground": null, "memorial": null }, "geometry": { "type": "Point", "coordinates": [ -1.8685274, 52.5307799 ] } },
{ "type": "Feature", "properties": { "osm_id": 8520993917, "name": null, "amenity": "bench", "man_made": null, "leisure": null, "playground": null, "memorial": null }, "geometry": { "type": "Point", "coordinates": [ -1.8685891, 52.530786 ] } }
]
}
