{
"type": "FeatureCollection",
"name": "BIRMI_16706",
"crs": { "type": "name", "properties": { "name": "urn:ogc:def:crs:OGC:1.3:CRS84" } },
"features": [
{ "type": "Feature", "properties": { "osm_id": 12578870121, "name": null, "amenity": "bench", "man_made": null, "leisure": null, "playground": null, "memorial": null }, "geometry": { "type": "Point", "coordinates": [ -1.9235855, 52.4612013 ] } },
{ "type": "Feature", "properties": { "osm_id": 11829232116, "name": null, "amenity": "bench", "man_made": null, "leisure": null, "playground": null, "memorial": null }, "geometry": { "type": "Point", "coordinates": [ -1.9243882, 52.4612046 ] } },
{ "type": "Feature", "properties": { "osm_id": 12229531267, "name": null, "amenity": "bench", "man_made": null, "leisure": null, "playground": null, "memorial": null }, "geometry": { "type": "Point", "coordinates": [ -1.9224733, 52.4612144 ] } },
{ "type": "Feature", "properties": { "osm_id": 11829212520, "name": null, "amenity": "bench", "man_made": null, "leisure": null, "playground": null, "memorial": null }, "geometry": { "type": "Point", "coordinates": [ -1.9226929, 52.4617687 ] } }
]
}
