{
"type": "FeatureCollection",
"name": "cbe254fcf698_visibility",
"crs": { "type": "name", "properties": { "name": "urn:ogc:def:crs:OGC:1.3:CRS84" } },
"features": [
{ "type": "Feature", "properties": { "visible_points": 6, "total_points": 40, "visibility_pct": 15.0 }, "geometry": { "type": "Point", "coordinates": [ -1.933766225406196, 52.451331322350512 ] } },
{ "type": "Feature", "properties": { "visible_points": 8, "total_points": 48, "visibility_pct": 16.666666666666664 }, "geometry": { "type": "Point", "coordinates": [ -1.933562335387381, 52.45133120738344 ] } },
{ "type": "Feature", "properties": { "visible_points": 9, "total_points": 54, "visibility_pct": 16.666666666666664 }, "geometry": { "type": "Point", "coordinates": [ -1.933358445369903, 52.451331092064876 ] } },
{ "type": "Feature", "properties": { "visible_points": 4, "total_points": 57, "visibility_pct": 7.0175438596491224 }, "geometry": { "type": "Point", "coordinates": [ -1.93315455535376, 52.451330976394829 ] } },
{ "type": "Feature", "properties": { "visible_points": 6, "total_points": 58, "visibility_pct": 10.344827586206897 }, "geometry": { "type": "Point", "coordinates": [ -1.932950665338971, 52.451330860373297 ] } },
{ "type": "Feature", "properties": { "visible_points": 7, "total_points": 56, "visibility_pct": 12.5 }, "geometry": { "type": "Point", "coordinates": [ -1.932746775325524, 52.451330744000273 ] } },
{ "type": "Feature", "properties": { "visible_points": 9, "total_points": 45, "visibility_pct": 20.0 }, "geometry": { "type": "Point", "coordinates": [ -1.93366411995133, 52.451439145582825 ] } },
{ "type": "Feature", "properties": { "visible_points": 8, "total_points": 53, "visibility_pct": 15.09433962264151 }, "geometry": { "type": "Point", "coordinates": [ -1.933460229456511, 52.451439030435417 ] } },
{ "type": "Feature", "properties": { "visible_points": 10, "total_points": 57, "visibility_pct": 17.543859649122805 }, "geometry": { "type": "Point", "coordinates": [ -1.933256338963028, 52.451438914936524 ] } },
{ "type": "Feature", "properties": { "visible_points": 12, "total_points": 58, "visibility_pct": 20.689655172413794 }, "geometry": { "type": "Point", "coordinates": [ -1.933052448470889, 52.451438799086148 ] } },
{ "type": "Feature", "properties": { "visible_points": 13, "total_points": 58, "visibility_pct": 22.413793103448278 }, "geometry": { "type": "Point", "coordinates": [ -1.932848557980099, 52.45143868288428 ] } },
{ "type": "Feature", "properties": { "visible_points": 5, "total_points": 54, "visibility_pct": 9.2592592592592595 }, "geometry": { "type": "Point", "coordinates": [ -1.932644667490652, 52.451438566330935 ] } },
{ "type": "Feature", "properties": { "visible_points": 7, "total_points": 58, "visibility_pct": 12.068965517241379 }, "geometry": { "type": "Point", "coordinates": [ -1.932950341110649, 52.451546621683029 ] } },
{ "type": "Feature", "properties": { "visible_points": 7, "total_points": 55, "visibility_pct": 12.727272727272727 }, "geometry": { "type": "Point", "coordinates": [ -1.93274645014386, 52.451546505300833 ] } },
{ "type": "Feature", "properties": { "visible_points": 10, "total_points": 50, "visibility_pct": 20.0 }, "geometry": { "type": "Point", "coordinates": [ -1.932542559178419, 52.451546388567152 ] } },
{ "type": "Feature", "properties": { "visible_points": 1, "total_points": 58, "visibility_pct": 1.7241379310344827 }, "geometry": { "type": "Point", "coordinates": [ -1.933052124717202, 52.451654560396513 ] } },
{ "type": "Feature", "properties": { "visible_points": 8, "total_points": 56, "visibility_pct": 14.285714285714285 }, "geometry": { "type": "Point", "coordinates": [ -1.932848233273053, 52.451654444185479 ] } },
{ "type": "Feature", "properties": { "visible_points": 6, "total_points": 51, "visibility_pct": 11.76470588235294 }, "geometry": { "type": "Point", "coordinates": [ -1.932644341830253, 52.45165432762294 ] } },
{ "type": "Feature", "properties": { "visible_points": 5, "total_points": 45, "visibility_pct": 11.111111111111111 }, "geometry": { "type": "Point", "coordinates": [ -1.932440450388815, 52.451654210708931 ] } },
{ "type": "Feature", "properties": { "visible_points": 13, "total_points": 55, "visibility_pct": 23.636363636363637 }, "geometry": { "type": "Point", "coordinates": [ -1.932950016878236, 52.45176238298486 ] } },
{ "type": "Feature", "properties": { "visible_points": 8, "total_points": 50, "visibility_pct": 16.0 }, "geometry": { "type": "Point", "coordinates": [ -1.93274612495808, 52.451762266593491 ] } }
]
}
