{
"type": "FeatureCollection",
"name": "f9dafbf38e84_visibility",
"crs": { "type": "name", "properties": { "name": "urn:ogc:def:crs:OGC:1.3:CRS84" } },
"features": [
{ "type": "Feature", "properties": { "visible_points": 7, "total_points": 47, "visibility_pct": 14.893617021276595 }, "geometry": { "type": "Point", "coordinates": [ -1.89970768204883, 52.505805472605552 ] } },
{ "type": "Feature", "properties": { "visible_points": 9, "total_points": 51, "visibility_pct": 17.647058823529413 }, "geometry": { "type": "Point", "coordinates": [ -1.899503543055989, 52.505805298709213 ] } },
{ "type": "Feature", "properties": { "visible_points": 6, "total_points": 53, "visibility_pct": 11.320754716981133 }, "geometry": { "type": "Point", "coordinates": [ -1.899299404065277, 52.505805124460686 ] } },
{ "type": "Feature", "properties": { "visible_points": 9, "total_points": 46, "visibility_pct": 19.565217391304348 }, "geometry": { "type": "Point", "coordinates": [ -1.899809508570371, 52.505913440136496 ] } },
{ "type": "Feature", "properties": { "visible_points": 10, "total_points": 50, "visibility_pct": 20.0 }, "geometry": { "type": "Point", "coordinates": [ -1.899605369065189, 52.505913266418645 ] } },
{ "type": "Feature", "properties": { "visible_points": 11, "total_points": 53, "visibility_pct": 20.754716981132077 }, "geometry": { "type": "Point", "coordinates": [ -1.899401229562142, 52.505913092348564 ] } },
{ "type": "Feature", "properties": { "visible_points": 13, "total_points": 53, "visibility_pct": 24.528301886792452 }, "geometry": { "type": "Point", "coordinates": [ -1.89919709006121, 52.505912917926288 ] } },
{ "type": "Feature", "properties": { "visible_points": 4, "total_points": 52, "visibility_pct": 7.6923076923076925 }, "geometry": { "type": "Point", "coordinates": [ -1.898992950562422, 52.505912743151818 ] } },
{ "type": "Feature", "properties": { "visible_points": 1, "total_points": 44, "visibility_pct": 2.2727272727272729 }, "geometry": { "type": "Point", "coordinates": [ -1.899911335602117, 52.506021407575076 ] } },
{ "type": "Feature", "properties": { "visible_points": 7, "total_points": 49, "visibility_pct": 14.285714285714285 }, "geometry": { "type": "Point", "coordinates": [ -1.899707195584593, 52.506021234035671 ] } },
{ "type": "Feature", "properties": { "visible_points": 10, "total_points": 53, "visibility_pct": 18.867924528301888 }, "geometry": { "type": "Point", "coordinates": [ -1.899503055569196, 52.50602106014405 ] } },
{ "type": "Feature", "properties": { "visible_points": 12, "total_points": 53, "visibility_pct": 22.641509433962266 }, "geometry": { "type": "Point", "coordinates": [ -1.899298915555923, 52.506020885900234 ] } },
{ "type": "Feature", "properties": { "visible_points": 10, "total_points": 53, "visibility_pct": 18.867924528301888 }, "geometry": { "type": "Point", "coordinates": [ -1.899094775544786, 52.506020711304245 ] } },
{ "type": "Feature", "properties": { "visible_points": 8, "total_points": 48, "visibility_pct": 16.666666666666664 }, "geometry": { "type": "Point", "coordinates": [ -1.898890635535786, 52.50602053635604 ] } },
{ "type": "Feature", "properties": { "visible_points": 4, "total_points": 41, "visibility_pct": 9.7560975609756095 }, "geometry": { "type": "Point", "coordinates": [ -1.898686495528925, 52.50602036105564 ] } },
{ "type": "Feature", "properties": { "visible_points": 3, "total_points": 46, "visibility_pct": 6.5217391304347823 }, "geometry": { "type": "Point", "coordinates": [ -1.899809022614206, 52.506129201560306 ] } },
{ "type": "Feature", "properties": { "visible_points": 0, "total_points": 51, "visibility_pct": 0.0 }, "geometry": { "type": "Point", "coordinates": [ -1.899604882086458, 52.50612902784718 ] } },
{ "type": "Feature", "properties": { "visible_points": 9, "total_points": 53, "visibility_pct": 16.981132075471699 }, "geometry": { "type": "Point", "coordinates": [ -1.899400741560838, 52.506128853781831 ] } },
{ "type": "Feature", "properties": { "visible_points": 7, "total_points": 53, "visibility_pct": 13.20754716981132 }, "geometry": { "type": "Point", "coordinates": [ -1.899196601037351, 52.506128679364281 ] } },
{ "type": "Feature", "properties": { "visible_points": 4, "total_points": 50, "visibility_pct": 8.0 }, "geometry": { "type": "Point", "coordinates": [ -1.898992460515997, 52.50612850459455 ] } },
{ "type": "Feature", "properties": { "visible_points": 0, "total_points": 43, "visibility_pct": 0.0 }, "geometry": { "type": "Point", "coordinates": [ -1.898788319996781, 52.506128329472595 ] } }
]
}
