{
"type": "FeatureCollection",
"name": "14533e591b7a_visibility",
"crs": { "type": "name", "properties": { "name": "urn:ogc:def:crs:OGC:1.3:CRS84" } },
"features": [
{ "type": "Feature", "properties": { "visible_points": 7, "total_points": 47, "visibility_pct": 14.893617021276595 }, "geometry": { "type": "Point", "coordinates": [ -2.373901926749185, 52.663972128857466 ] } },
{ "type": "Feature", "properties": { "visible_points": 8, "total_points": 48, "visibility_pct": 16.666666666666664 }, "geometry": { "type": "Point", "coordinates": [ -2.37369704742872, 52.663972775075827 ] } },
{ "type": "Feature", "properties": { "visible_points": 2, "total_points": 47, "visibility_pct": 4.2553191489361701 }, "geometry": { "type": "Point", "coordinates": [ -2.37349216810054, 52.663973420940025 ] } },
{ "type": "Feature", "properties": { "visible_points": 8, "total_points": 50, "visibility_pct": 16.0 }, "geometry": { "type": "Point", "coordinates": [ -2.374005287302063, 52.664079678895469 ] } },
{ "type": "Feature", "properties": { "visible_points": 8, "total_points": 51, "visibility_pct": 15.686274509803921 }, "geometry": { "type": "Point", "coordinates": [ -2.37380040748716, 52.664080325294165 ] } },
{ "type": "Feature", "properties": { "visible_points": 8, "total_points": 51, "visibility_pct": 15.686274509803921 }, "geometry": { "type": "Point", "coordinates": [ -2.373595527664553, 52.664080971338706 ] } },
{ "type": "Feature", "properties": { "visible_points": 0, "total_points": 48, "visibility_pct": 0.0 }, "geometry": { "type": "Point", "coordinates": [ -2.374313528658698, 52.664186581906471 ] } },
{ "type": "Feature", "properties": { "visible_points": 8, "total_points": 51, "visibility_pct": 15.686274509803921 }, "geometry": { "type": "Point", "coordinates": [ -2.374108648357085, 52.664187228839666 ] } },
{ "type": "Feature", "properties": { "visible_points": 9, "total_points": 51, "visibility_pct": 17.647058823529413 }, "geometry": { "type": "Point", "coordinates": [ -2.373903768047746, 52.664187875418705 ] } },
{ "type": "Feature", "properties": { "visible_points": 6, "total_points": 51, "visibility_pct": 11.76470588235294 }, "geometry": { "type": "Point", "coordinates": [ -2.373698887730692, 52.664188521643595 ] } },
{ "type": "Feature", "properties": { "visible_points": 3, "total_points": 51, "visibility_pct": 5.8823529411764701 }, "geometry": { "type": "Point", "coordinates": [ -2.37349400740593, 52.66418916751433 ] } },
{ "type": "Feature", "properties": { "visible_points": 0, "total_points": 50, "visibility_pct": 0.0 }, "geometry": { "type": "Point", "coordinates": [ -2.374212009914253, 52.664294778690099 ] } },
{ "type": "Feature", "properties": { "visible_points": 9, "total_points": 51, "visibility_pct": 17.647058823529413 }, "geometry": { "type": "Point", "coordinates": [ -2.374007129110481, 52.664295425449488 ] } },
{ "type": "Feature", "properties": { "visible_points": 7, "total_points": 51, "visibility_pct": 13.725490196078432 }, "geometry": { "type": "Point", "coordinates": [ -2.373802248298984, 52.664296071854707 ] } },
{ "type": "Feature", "properties": { "visible_points": 6, "total_points": 51, "visibility_pct": 11.76470588235294 }, "geometry": { "type": "Point", "coordinates": [ -2.373597367479778, 52.664296717905756 ] } },
{ "type": "Feature", "properties": { "visible_points": 0, "total_points": 51, "visibility_pct": 0.0 }, "geometry": { "type": "Point", "coordinates": [ -2.373392486652858, 52.664297363602671 ] } },
{ "type": "Feature", "properties": { "visible_points": 0, "total_points": 50, "visibility_pct": 0.0 }, "geometry": { "type": "Point", "coordinates": [ -2.373905609369426, 52.664403621972028 ] } },
{ "type": "Feature", "properties": { "visible_points": 4, "total_points": 51, "visibility_pct": 7.8431372549019605 }, "geometry": { "type": "Point", "coordinates": [ -2.373700728055772, 52.664404268203427 ] } },
{ "type": "Feature", "properties": { "visible_points": 2, "total_points": 51, "visibility_pct": 3.9215686274509802 }, "geometry": { "type": "Point", "coordinates": [ -2.373495846734406, 52.664404914080656 ] } },
{ "type": "Feature", "properties": { "visible_points": 0, "total_points": 47, "visibility_pct": 0.0 }, "geometry": { "type": "Point", "coordinates": [ -2.373804089133923, 52.664511818407298 ] } },
{ "type": "Feature", "properties": { "visible_points": 0, "total_points": 47, "visibility_pct": 0.0 }, "geometry": { "type": "Point", "coordinates": [ -2.373599207318101, 52.664512464464877 ] } },
{ "type": "Feature", "properties": { "visible_points": 1, "total_points": 43, "visibility_pct": 2.3255813953488373 }, "geometry": { "type": "Point", "coordinates": [ -2.37339432549458, 52.664513110168301 ] } }
]
}
