{
"type": "FeatureCollection",
"name": "b47dda4504ca_visibility",
"crs": { "type": "name", "properties": { "name": "urn:ogc:def:crs:OGC:1.3:CRS84" } },
"features": [
{ "type": "Feature", "properties": { "visible_points": 1, "total_points": 48, "visibility_pct": 2.083333333333333 }, "geometry": { "type": "Point", "coordinates": [ -2.779999343857888, 52.713566638473381 ] } },
{ "type": "Feature", "properties": { "visible_points": 0, "total_points": 48, "visibility_pct": 0.0 }, "geometry": { "type": "Point", "coordinates": [ -2.779794251228415, 52.713567984993198 ] } },
{ "type": "Feature", "properties": { "visible_points": 2, "total_points": 48, "visibility_pct": 4.1666666666666661 }, "geometry": { "type": "Point", "coordinates": [ -2.779589158582866, 52.713569331159107 ] } },
{ "type": "Feature", "properties": { "visible_points": 0, "total_points": 48, "visibility_pct": 0.0 }, "geometry": { "type": "Point", "coordinates": [ -2.780103813827997, 52.713673833339371 ] } },
{ "type": "Feature", "properties": { "visible_points": 0, "total_points": 48, "visibility_pct": 0.0 }, "geometry": { "type": "Point", "coordinates": [ -2.779898720709639, 52.713675180074304 ] } },
{ "type": "Feature", "properties": { "visible_points": 1, "total_points": 48, "visibility_pct": 2.083333333333333 }, "geometry": { "type": "Point", "coordinates": [ -2.77969362757519, 52.713676526455323 ] } },
{ "type": "Feature", "properties": { "visible_points": 2, "total_points": 48, "visibility_pct": 4.1666666666666661 }, "geometry": { "type": "Point", "coordinates": [ -2.779488534424655, 52.713677872482414 ] } },
{ "type": "Feature", "properties": { "visible_points": 0, "total_points": 47, "visibility_pct": 0.0 }, "geometry": { "type": "Point", "coordinates": [ -2.780413377894241, 52.713779680772127 ] } },
{ "type": "Feature", "properties": { "visible_points": 0, "total_points": 48, "visibility_pct": 0.0 }, "geometry": { "type": "Point", "coordinates": [ -2.780208284303087, 52.713781028076099 ] } },
{ "type": "Feature", "properties": { "visible_points": 0, "total_points": 48, "visibility_pct": 0.0 }, "geometry": { "type": "Point", "coordinates": [ -2.780003190695835, 52.713782375026149 ] } },
{ "type": "Feature", "properties": { "visible_points": 0, "total_points": 48, "visibility_pct": 0.0 }, "geometry": { "type": "Point", "coordinates": [ -2.77979809707249, 52.713783721622256 ] } },
{ "type": "Feature", "properties": { "visible_points": 0, "total_points": 48, "visibility_pct": 0.0 }, "geometry": { "type": "Point", "coordinates": [ -2.779593003433055, 52.713785067864464 ] } },
{ "type": "Feature", "properties": { "visible_points": 0, "total_points": 47, "visibility_pct": 0.0 }, "geometry": { "type": "Point", "coordinates": [ -2.780312755283164, 52.713888222683572 ] } },
{ "type": "Feature", "properties": { "visible_points": 0, "total_points": 48, "visibility_pct": 0.0 }, "geometry": { "type": "Point", "coordinates": [ -2.780107661187011, 52.713889569848725 ] } },
{ "type": "Feature", "properties": { "visible_points": 2, "total_points": 48, "visibility_pct": 4.1666666666666661 }, "geometry": { "type": "Point", "coordinates": [ -2.779902567074767, 52.713890916659956 ] } },
{ "type": "Feature", "properties": { "visible_points": 2, "total_points": 48, "visibility_pct": 4.1666666666666661 }, "geometry": { "type": "Point", "coordinates": [ -2.779697472946437, 52.713892263117266 ] } },
{ "type": "Feature", "properties": { "visible_points": 2, "total_points": 48, "visibility_pct": 4.1666666666666661 }, "geometry": { "type": "Point", "coordinates": [ -2.779492378802015, 52.713893609220655 ] } },
{ "type": "Feature", "properties": { "visible_points": 0, "total_points": 48, "visibility_pct": 0.0 }, "geometry": { "type": "Point", "coordinates": [ -2.780007037582032, 52.713998111568372 ] } },
{ "type": "Feature", "properties": { "visible_points": 0, "total_points": 48, "visibility_pct": 0.0 }, "geometry": { "type": "Point", "coordinates": [ -2.779801942964796, 52.713999458240814 ] } },
{ "type": "Feature", "properties": { "visible_points": 0, "total_points": 48, "visibility_pct": 0.0 }, "geometry": { "type": "Point", "coordinates": [ -2.779596848331475, 52.714000804559312 ] } },
{ "type": "Feature", "properties": { "visible_points": 2, "total_points": 44, "visibility_pct": 4.5454545454545459 }, "geometry": { "type": "Point", "coordinates": [ -2.779906413488146, 52.714106653235071 ] } }
]
}
