{
"type": "FeatureCollection",
"name": "WALSA_55",
"crs": { "type": "name", "properties": { "name": "urn:ogc:def:crs:OGC:1.3:CRS84" } },
"features": [
{ "type": "Feature", "properties": { "osm_id": 4308070481, "name": null, "amenity": "bench", "man_made": null, "leisure": null, "playground": null, "memorial": null }, "geometry": { "type": "Point", "coordinates": [ -1.9234365, 52.6058584 ] } }
]
}
