{
"type": "FeatureCollection",
"name": "WALSA_51",
"crs": { "type": "name", "properties": { "name": "urn:ogc:def:crs:OGC:1.3:CRS84" } },
"features": [
{ "type": "Feature", "properties": { "osm_id": 7494498685, "name": null, "amenity": "bench", "man_made": null, "leisure": null, "playground": null, "memorial": null }, "geometry": { "type": "Point", "coordinates": [ -1.9482741, 52.5801914 ] } },
{ "type": "Feature", "properties": { "osm_id": 7489765085, "name": null, "amenity": "bench", "man_made": null, "leisure": null, "playground": null, "memorial": null }, "geometry": { "type": "Point", "coordinates": [ -1.9594245, 52.5846381 ] } },
{ "type": "Feature", "properties": { "osm_id": 7494498585, "name": null, "amenity": "bench", "man_made": null, "leisure": null, "playground": null, "memorial": null }, "geometry": { "type": "Point", "coordinates": [ -1.964948, 52.5883349 ] } },
{ "type": "Feature", "properties": { "osm_id": 12177464008, "name": null, "amenity": "bench", "man_made": null, "leisure": null, "playground": null, "memorial": null }, "geometry": { "type": "Point", "coordinates": [ -1.9744369, 52.5887783 ] } }
]
}
