{
"type": "FeatureCollection",
"name": "WYRFO_27",
"crs": { "type": "name", "properties": { "name": "urn:ogc:def:crs:OGC:1.3:CRS84" } },
"features": [
{ "type": "Feature", "properties": { "osm_id": 4880252491, "name": null, "amenity": "bench", "man_made": null, "leisure": null, "playground": null, "memorial": null }, "geometry": { "type": "Point", "coordinates": [ -2.2772033, 52.3406772 ] } },
{ "type": "Feature", "properties": { "osm_id": 4880252492, "name": null, "amenity": "bench", "man_made": null, "leisure": null, "playground": null, "memorial": null }, "geometry": { "type": "Point", "coordinates": [ -2.2771148, 52.3407063 ] } },
{ "type": "Feature", "properties": { "osm_id": 4880252493, "name": null, "amenity": "bench", "man_made": null, "leisure": null, "playground": null, "memorial": null }, "geometry": { "type": "Point", "coordinates": [ -2.2769243, 52.3407755 ] } }
]
}
