{
"type": "FeatureCollection",
"name": "COVEN_30_toilets",
"crs": { "type": "name", "properties": { "name": "urn:ogc:def:crs:OGC:1.3:CRS84" } },
"features": [
{ "type": "Feature", "properties": { "name": "tesco", "payment_info": "Free", "accessible": "False", "radar": "Unknown", "women": "True", "men": "True", "baby_change": "Unknown", "Mon": "06:00-23:59", "Tue": "06:00-23:59", "Wed": "06:00-23:59", "Thu": "06:00-23:59", "Fri": "06:00-23:59", "Sat": "06:00-23:59", "Sun": "10:00-16:00", "index_right": 122, "park_offical_id": "COVEN_30" }, "geometry": { "type": "Point", "coordinates": [ -1.492048502, 52.443453326 ] } },
{ "type": "Feature", "properties": { "name": "Marks and Spencer", "payment_info": "Cost unknown", "accessible": "True", "radar": "False", "women": "True", "men": "True", "baby_change": "True", "Mon": "09:00-17:00", "Tue": "09:00-17:00", "Wed": "09:00-17:00", "Thu": "09:00-17:00", "Fri": "09:00-17:00", "Sat": "09:00-17:00", "Sun": "09:00-17:00", "index_right": 122, "park_offical_id": "COVEN_30" }, "geometry": { "type": "Point", "coordinates": [ -1.492726137, 52.445590529 ] } }
]
}
