{
"type": "FeatureCollection",
"name": "COVEN_35_toilets",
"crs": { "type": "name", "properties": { "name": "urn:ogc:def:crs:OGC:1.3:CRS84" } },
"features": [
{ "type": "Feature", "properties": { "name": "War Memorial Park Visitor Centre Caf  Sports Pavilion", "payment_info": "Free", "accessible": "False", "radar": "True", "women": "True", "men": "True", "baby_change": "True", "Mon": "09:00-19:30", "Tue": "09:00-19:30", "Wed": "09:00-19:30", "Thu": "09:00-19:30", "Fri": "09:00-19:30", "Sat": "09:00-19:30", "Sun": "09:00-19:30", "index_right": 127, "park_offical_id": "COVEN_35" }, "geometry": { "type": "Point", "coordinates": [ -1.523923874, 52.391266714 ] } },
{ "type": "Feature", "properties": { "name": "Albany Road", "payment_info": "Cost unknown", "accessible": "False", "radar": "True", "women": "True", "men": "True", "baby_change": "Unknown", "Mon": "07:30-20:00", "Tue": "07:30-20:00", "Wed": "07:30-20:00", "Thu": "07:30-20:00", "Fri": "07:30-20:00", "Sat": "07:30-20:00", "Sun": "Closed", "index_right": 127, "park_offical_id": "COVEN_35" }, "geometry": { "type": "Point", "coordinates": [ -1.528190042, 52.400532754 ] } },
{ "type": "Feature", "properties": { "name": "War Memorial Park Caf  Tennis Pavilion", "payment_info": "Free", "accessible": "True", "radar": "True", "women": "True", "men": "True", "baby_change": "True", "Mon": "09:00-19:30", "Tue": "09:00-19:30", "Wed": "09:00-19:30", "Thu": "09:00-19:30", "Fri": "09:00-19:30", "Sat": "09:00-19:30", "Sun": "09:00-19:30", "index_right": 127, "park_offical_id": "COVEN_35" }, "geometry": { "type": "Point", "coordinates": [ -1.5213198, 52.3945197 ] } },
{ "type": "Feature", "properties": { "name": "Coventry Train Station", "payment_info": "Free", "accessible": "True", "radar": "True", "women": "True", "men": "True", "baby_change": "True", "Mon": "05:15-01:30", "Tue": "05:15-01:30", "Wed": "05:15-01:30", "Thu": "05:15-01:30", "Fri": "05:15-01:30", "Sat": "05:30-12:30", "Sun": "07:30-01:30", "index_right": 127, "park_offical_id": "COVEN_35" }, "geometry": { "type": "Point", "coordinates": [ -1.514208913, 52.401057329 ] } }
]
}
