{
"type": "FeatureCollection",
"name": "COVEN_174_toilets",
"crs": { "type": "name", "properties": { "name": "urn:ogc:def:crs:OGC:1.3:CRS84" } },
"features": [
{ "type": "Feature", "properties": { "name": "Nursery Tavern", "payment_info": "nil", "accessible": "True", "radar": "False", "women": "True", "men": "True", "baby_change": "False", "Mon": "Unknown", "Tue": "Unknown", "Wed": "Unknown", "Thu": "Unknown", "Fri": "Unknown", "Sat": "Unknown", "Sun": "Unknown", "index_right": 57, "park_offical_id": "COVEN_174" }, "geometry": { "type": "Point", "coordinates": [ -1.533536911, 52.407910449 ] } },
{ "type": "Feature", "properties": { "name": "Belgrade Theatre", "payment_info": "Cost unknown", "accessible": "True", "radar": "True", "women": "True", "men": "True", "baby_change": "True", "Mon": "10:00-17:30", "Tue": "10:00-17:30", "Wed": "10:00-17:30", "Thu": "10:00-17:30", "Fri": "10:00-17:30", "Sat": "10:00-17:30", "Sun": "Closed", "index_right": 57, "park_offical_id": "COVEN_174" }, "geometry": { "type": "Point", "coordinates": [ -1.514203548, 52.409860808 ] } }
]
}
