{
"type": "FeatureCollection",
"name": "COVEN_204_toilets",
"crs": { "type": "name", "properties": { "name": "urn:ogc:def:crs:OGC:1.3:CRS84" } },
"features": [
{ "type": "Feature", "properties": { "name": "Pool Meadow Bus Station", "payment_info": "Free", "accessible": "True", "radar": "True", "women": "True", "men": "True", "baby_change": "True", "Mon": "00:00-00:00", "Tue": "00:00-00:00", "Wed": "00:00-00:00", "Thu": "00:00-00:00", "Fri": "00:00-00:00", "Sat": "00:00-00:00", "Sun": "00:00-00:00", "index_right": 84, "park_offical_id": "COVEN_204" }, "geometry": { "type": "Point", "coordinates": [ -1.507122517, 52.40996225 ] } },
{ "type": "Feature", "properties": { "name": "Coventry Transport Museum", "payment_info": "see notes", "accessible": "True", "radar": "True", "women": "True", "men": "True", "baby_change": "True", "Mon": "10:00-17:00", "Tue": "10:00-17:00", "Wed": "10:00-17:00", "Thu": "10:00-17:00", "Fri": "10:00-17:00", "Sat": "10:00-17:00", "Sun": "10:00-17:00", "index_right": 84, "park_offical_id": "COVEN_204" }, "geometry": { "type": "Point", "coordinates": [ -1.509515047, 52.410767237 ] } },
{ "type": "Feature", "properties": { "name": "Coventry Cathedral", "payment_info": "Free", "accessible": "True", "radar": "True", "women": "True", "men": "True", "baby_change": "True", "Mon": "10:00-16:00", "Tue": "10:00-16:00", "Wed": "10:00-16:00", "Thu": "10:00-16:00", "Fri": "10:00-16:00", "Sat": "10:00-16:00", "Sun": "12:30-15:00", "index_right": 84, "park_offical_id": "COVEN_204" }, "geometry": { "type": "Point", "coordinates": [ -1.506913304, 52.408980539 ] } }
]
}
