{
"type": "FeatureCollection",
"name": "d142ccab66b9_visibility",
"crs": { "type": "name", "properties": { "name": "urn:ogc:def:crs:OGC:1.3:CRS84" } },
"features": [
{ "type": "Feature", "properties": { "visible_points": 10, "total_points": 44, "visibility_pct": 22.727272727272727 }, "geometry": { "type": "Point", "coordinates": [ -1.830075871007329, 52.683943615572431 ] } },
{ "type": "Feature", "properties": { "visible_points": 10, "total_points": 49, "visibility_pct": 20.408163265306122 }, "geometry": { "type": "Point", "coordinates": [ -1.829870899877945, 52.683943322420483 ] } },
{ "type": "Feature", "properties": { "visible_points": 15, "total_points": 45, "visibility_pct": 33.333333333333329 }, "geometry": { "type": "Point", "coordinates": [ -1.830177940293558, 52.684051637556173 ] } },
{ "type": "Feature", "properties": { "visible_points": 18, "total_points": 50, "visibility_pct": 36.0 }, "geometry": { "type": "Point", "coordinates": [ -1.82997296865405, 52.684051344577746 ] } },
{ "type": "Feature", "properties": { "visible_points": 12, "total_points": 54, "visibility_pct": 22.222222222222221 }, "geometry": { "type": "Point", "coordinates": [ -1.829767997018128, 52.684051051244879 ] } },
{ "type": "Feature", "properties": { "visible_points": 5, "total_points": 56, "visibility_pct": 8.9285714285714288 }, "geometry": { "type": "Point", "coordinates": [ -1.82956302538579, 52.684050757557607 ] } },
{ "type": "Feature", "properties": { "visible_points": 18, "total_points": 49, "visibility_pct": 36.734693877551024 }, "geometry": { "type": "Point", "coordinates": [ -1.830075037936678, 52.684159366648117 ] } },
{ "type": "Feature", "properties": { "visible_points": 15, "total_points": 54, "visibility_pct": 27.777777777777779 }, "geometry": { "type": "Point", "coordinates": [ -1.829870065790631, 52.684159073488779 ] } },
{ "type": "Feature", "properties": { "visible_points": 16, "total_points": 56, "visibility_pct": 28.571428571428569 }, "geometry": { "type": "Point", "coordinates": [ -1.829665093648165, 52.684158779975 ] } },
{ "type": "Feature", "properties": { "visible_points": 6, "total_points": 56, "visibility_pct": 10.714285714285714 }, "geometry": { "type": "Point", "coordinates": [ -1.829460121509292, 52.684158486106782 ] } },
{ "type": "Feature", "properties": { "visible_points": 1, "total_points": 52, "visibility_pct": 1.9230769230769231 }, "geometry": { "type": "Point", "coordinates": [ -1.829255149374015, 52.684158191884137 ] } },
{ "type": "Feature", "properties": { "visible_points": 15, "total_points": 56, "visibility_pct": 26.785714285714285 }, "geometry": { "type": "Point", "coordinates": [ -1.829767162417069, 52.684266802305508 ] } },
{ "type": "Feature", "properties": { "visible_points": 15, "total_points": 56, "visibility_pct": 26.785714285714285 }, "geometry": { "type": "Point", "coordinates": [ -1.829562189768062, 52.684266508610811 ] } },
{ "type": "Feature", "properties": { "visible_points": 0, "total_points": 53, "visibility_pct": 0.0 }, "geometry": { "type": "Point", "coordinates": [ -1.829357217122646, 52.684266214561681 ] } },
{ "type": "Feature", "properties": { "visible_points": 1, "total_points": 48, "visibility_pct": 2.083333333333333 }, "geometry": { "type": "Point", "coordinates": [ -1.829152244480831, 52.684265920158126 ] } },
{ "type": "Feature", "properties": { "visible_points": 13, "total_points": 52, "visibility_pct": 25.0 }, "geometry": { "type": "Point", "coordinates": [ -1.829459285377806, 52.684374237152333 ] } },
{ "type": "Feature", "properties": { "visible_points": 0, "total_points": 47, "visibility_pct": 0.0 }, "geometry": { "type": "Point", "coordinates": [ -1.82925431222585, 52.684373942922285 ] } },
{ "type": "Feature", "properties": { "visible_points": 1, "total_points": 42, "visibility_pct": 2.3809523809523809 }, "geometry": { "type": "Point", "coordinates": [ -1.829049339077491, 52.684373648337818 ] } },
{ "type": "Feature", "properties": { "visible_points": 12, "total_points": 45, "visibility_pct": 26.666666666666668 }, "geometry": { "type": "Point", "coordinates": [ -1.8293563804774, 52.684481965599559 ] } },
{ "type": "Feature", "properties": { "visible_points": 0, "total_points": 41, "visibility_pct": 0.0 }, "geometry": { "type": "Point", "coordinates": [ -1.829151406818899, 52.684481671188585 ] } }
]
}
