{
"type": "FeatureCollection",
"name": "45bd6544ee41_visibility",
"crs": { "type": "name", "properties": { "name": "urn:ogc:def:crs:OGC:1.3:CRS84" } },
"features": [
{ "type": "Feature", "properties": { "visible_points": 5, "total_points": 43, "visibility_pct": 11.627906976744185 }, "geometry": { "type": "Point", "coordinates": [ -2.122780048342254, 52.990700525719561 ] } },
{ "type": "Feature", "properties": { "visible_points": 0, "total_points": 48, "visibility_pct": 0.0 }, "geometry": { "type": "Point", "coordinates": [ -2.122573626309311, 52.990700737990764 ] } },
{ "type": "Feature", "properties": { "visible_points": 7, "total_points": 51, "visibility_pct": 13.725490196078432 }, "geometry": { "type": "Point", "coordinates": [ -2.122367204273795, 52.990700949903577 ] } },
{ "type": "Feature", "properties": { "visible_points": 5, "total_points": 52, "visibility_pct": 9.6153846153846168 }, "geometry": { "type": "Point", "coordinates": [ -2.122160782235703, 52.990701161457991 ] } },
{ "type": "Feature", "properties": { "visible_points": 5, "total_points": 49, "visibility_pct": 10.204081632653061 }, "geometry": { "type": "Point", "coordinates": [ -2.122677141798124, 52.990808502297853 ] } },
{ "type": "Feature", "properties": { "visible_points": 8, "total_points": 52, "visibility_pct": 15.384615384615385 }, "geometry": { "type": "Point", "coordinates": [ -2.122470719251246, 52.990808714390418 ] } },
{ "type": "Feature", "properties": { "visible_points": 7, "total_points": 52, "visibility_pct": 13.461538461538462 }, "geometry": { "type": "Point", "coordinates": [ -2.122264296701793, 52.990808926124572 ] } },
{ "type": "Feature", "properties": { "visible_points": 0, "total_points": 52, "visibility_pct": 0.0 }, "geometry": { "type": "Point", "coordinates": [ -2.122057874149764, 52.990809137500364 ] } },
{ "type": "Feature", "properties": { "visible_points": 4, "total_points": 48, "visibility_pct": 8.3333333333333321 }, "geometry": { "type": "Point", "coordinates": [ -2.12278065780087, 52.990916266512848 ] } },
{ "type": "Feature", "properties": { "visible_points": 1, "total_points": 52, "visibility_pct": 1.9230769230769231 }, "geometry": { "type": "Point", "coordinates": [ -2.122574234742632, 52.990916478785152 ] } },
{ "type": "Feature", "properties": { "visible_points": 5, "total_points": 52, "visibility_pct": 9.6153846153846168 }, "geometry": { "type": "Point", "coordinates": [ -2.12236781168181, 52.990916690699059 ] } },
{ "type": "Feature", "properties": { "visible_points": 0, "total_points": 52, "visibility_pct": 0.0 }, "geometry": { "type": "Point", "coordinates": [ -2.122161388618415, 52.99091690225459 ] } },
{ "type": "Feature", "properties": { "visible_points": 8, "total_points": 52, "visibility_pct": 15.384615384615385 }, "geometry": { "type": "Point", "coordinates": [ -2.122264903600999, 52.991024666916687 ] } },
{ "type": "Feature", "properties": { "visible_points": 7, "total_points": 52, "visibility_pct": 13.461538461538462 }, "geometry": { "type": "Point", "coordinates": [ -2.122058480023663, 52.991024878293572 ] } },
{ "type": "Feature", "properties": { "visible_points": 2, "total_points": 49, "visibility_pct": 4.0816326530612246 }, "geometry": { "type": "Point", "coordinates": [ -2.121852056443762, 52.991025089312053 ] } },
{ "type": "Feature", "properties": { "visible_points": 0, "total_points": 51, "visibility_pct": 0.0 }, "geometry": { "type": "Point", "coordinates": [ -2.12216199500881, 52.991132643043301 ] } },
{ "type": "Feature", "properties": { "visible_points": 7, "total_points": 48, "visibility_pct": 14.583333333333334 }, "geometry": { "type": "Point", "coordinates": [ -2.121955570917534, 52.991132854241542 ] } },
{ "type": "Feature", "properties": { "visible_points": 3, "total_points": 43, "visibility_pct": 6.9767441860465116 }, "geometry": { "type": "Point", "coordinates": [ -2.121749146823688, 52.991133065081385 ] } },
{ "type": "Feature", "properties": { "visible_points": 3, "total_points": 44, "visibility_pct": 6.8181818181818175 }, "geometry": { "type": "Point", "coordinates": [ -2.122059085905243, 52.99124061907893 ] } },
{ "type": "Feature", "properties": { "visible_points": 2, "total_points": 40, "visibility_pct": 5.0 }, "geometry": { "type": "Point", "coordinates": [ -2.121852661300019, 52.991240830098512 ] } }
]
}
