{
"type": "FeatureCollection",
"name": "6e92700108d6_visibility",
"crs": { "type": "name", "properties": { "name": "urn:ogc:def:crs:OGC:1.3:CRS84" } },
"features": [
{ "type": "Feature", "properties": { "visible_points": 0, "total_points": 35, "visibility_pct": 0.0 }, "geometry": { "type": "Point", "coordinates": [ -2.095365417197924, 52.966168794606013 ] } },
{ "type": "Feature", "properties": { "visible_points": 1, "total_points": 36, "visibility_pct": 2.7777777777777777 }, "geometry": { "type": "Point", "coordinates": [ -2.095159105033686, 52.966168973252138 ] } },
{ "type": "Feature", "properties": { "visible_points": 0, "total_points": 40, "visibility_pct": 0.0 }, "geometry": { "type": "Point", "coordinates": [ -2.09526250085063, 52.966276757265071 ] } },
{ "type": "Feature", "properties": { "visible_points": 0, "total_points": 41, "visibility_pct": 0.0 }, "geometry": { "type": "Point", "coordinates": [ -2.095056188159385, 52.966276935758643 ] } },
{ "type": "Feature", "properties": { "visible_points": 0, "total_points": 46, "visibility_pct": 0.0 }, "geometry": { "type": "Point", "coordinates": [ -2.09515958397836, 52.966384719859086 ] } },
{ "type": "Feature", "properties": { "visible_points": 0, "total_points": 50, "visibility_pct": 0.0 }, "geometry": { "type": "Point", "coordinates": [ -2.095262980324338, 52.966492503841522 ] } },
{ "type": "Feature", "properties": { "visible_points": 2, "total_points": 51, "visibility_pct": 3.9215686274509802 }, "geometry": { "type": "Point", "coordinates": [ -2.095056666581109, 52.966492682388001 ] } },
{ "type": "Feature", "properties": { "visible_points": 0, "total_points": 56, "visibility_pct": 0.0 }, "geometry": { "type": "Point", "coordinates": [ -2.095160062929119, 52.966600466457919 ] } },
{ "type": "Feature", "properties": { "visible_points": 0, "total_points": 57, "visibility_pct": 0.0 }, "geometry": { "type": "Point", "coordinates": [ -2.094953748658876, 52.96660064485183 ] } },
{ "type": "Feature", "properties": { "visible_points": 0, "total_points": 58, "visibility_pct": 0.0 }, "geometry": { "type": "Point", "coordinates": [ -2.095057145008912, 52.966708429009259 ] } },
{ "type": "Feature", "properties": { "visible_points": 0, "total_points": 55, "visibility_pct": 0.0 }, "geometry": { "type": "Point", "coordinates": [ -2.095160541885958, 52.966816213048702 ] } },
{ "type": "Feature", "properties": { "visible_points": 0, "total_points": 54, "visibility_pct": 0.0 }, "geometry": { "type": "Point", "coordinates": [ -2.094954226563713, 52.966816391495506 ] } },
{ "type": "Feature", "properties": { "visible_points": 1, "total_points": 51, "visibility_pct": 1.9607843137254901 }, "geometry": { "type": "Point", "coordinates": [ -2.095057623440849, 52.966924175610899 ] } },
{ "type": "Feature", "properties": { "visible_points": 0, "total_points": 50, "visibility_pct": 0.0 }, "geometry": { "type": "Point", "coordinates": [ -2.094851307591331, 52.966924353903437 ] } },
{ "type": "Feature", "properties": { "visible_points": 1, "total_points": 46, "visibility_pct": 2.1739130434782608 }, "geometry": { "type": "Point", "coordinates": [ -2.09495470335911, 52.967032136506113 ] } },
{ "type": "Feature", "properties": { "visible_points": 0, "total_points": 45, "visibility_pct": 0.0 }, "geometry": { "type": "Point", "coordinates": [ -2.094748386987054, 52.967032314623026 ] } },
{ "type": "Feature", "properties": { "visible_points": 5, "total_points": 42, "visibility_pct": 11.904761904761903 }, "geometry": { "type": "Point", "coordinates": [ -2.095058097724928, 52.967139917234206 ] } },
{ "type": "Feature", "properties": { "visible_points": 5, "total_points": 41, "visibility_pct": 12.195121951219512 }, "geometry": { "type": "Point", "coordinates": [ -2.094851780850832, 52.967140095511752 ] } },
{ "type": "Feature", "properties": { "visible_points": 5, "total_points": 40, "visibility_pct": 12.5 }, "geometry": { "type": "Point", "coordinates": [ -2.094645463974776, 52.967140273431198 ] } },
{ "type": "Feature", "properties": { "visible_points": 6, "total_points": 38, "visibility_pct": 15.789473684210526 }, "geometry": { "type": "Point", "coordinates": [ -2.094955175162943, 52.967247875993671 ] } },
{ "type": "Feature", "properties": { "visible_points": 7, "total_points": 37, "visibility_pct": 18.918918918918919 }, "geometry": { "type": "Point", "coordinates": [ -2.094748857785523, 52.967248054071064 ] } }
]
}
