{
"type": "FeatureCollection",
"name": "9af6ad20f861_visibility",
"crs": { "type": "name", "properties": { "name": "urn:ogc:def:crs:OGC:1.3:CRS84" } },
"features": [
{ "type": "Feature", "properties": { "visible_points": 0, "total_points": 55, "visibility_pct": 0.0 }, "geometry": { "type": "Point", "coordinates": [ -2.159391344205704, 52.973062217163822 ] } },
{ "type": "Feature", "properties": { "visible_points": 5, "total_points": 52, "visibility_pct": 9.6153846153846168 }, "geometry": { "type": "Point", "coordinates": [ -2.159185007955795, 52.973062494312245 ] } },
{ "type": "Feature", "properties": { "visible_points": 0, "total_points": 47, "visibility_pct": 0.0 }, "geometry": { "type": "Point", "coordinates": [ -2.158978671702498, 52.973062771102505 ] } },
{ "type": "Feature", "properties": { "visible_points": 9, "total_points": 56, "visibility_pct": 16.071428571428573 }, "geometry": { "type": "Point", "coordinates": [ -2.159494910978894, 52.973169951381095 ] } },
{ "type": "Feature", "properties": { "visible_points": 10, "total_points": 56, "visibility_pct": 17.857142857142858 }, "geometry": { "type": "Point", "coordinates": [ -2.159288574213931, 52.973170228708007 ] } },
{ "type": "Feature", "properties": { "visible_points": 8, "total_points": 53, "visibility_pct": 15.09433962264151 }, "geometry": { "type": "Point", "coordinates": [ -2.159082237445576, 52.973170505676734 ] } },
{ "type": "Feature", "properties": { "visible_points": 0, "total_points": 48, "visibility_pct": 0.0 }, "geometry": { "type": "Point", "coordinates": [ -2.158875900673843, 52.973170782287291 ] } },
{ "type": "Feature", "properties": { "visible_points": 0, "total_points": 55, "visibility_pct": 0.0 }, "geometry": { "type": "Point", "coordinates": [ -2.159804815547151, 52.973277407643927 ] } },
{ "type": "Feature", "properties": { "visible_points": 6, "total_points": 56, "visibility_pct": 10.714285714285714 }, "geometry": { "type": "Point", "coordinates": [ -2.159598478270524, 52.973277685507483 ] } },
{ "type": "Feature", "properties": { "visible_points": 7, "total_points": 56, "visibility_pct": 12.5 }, "geometry": { "type": "Point", "coordinates": [ -2.159392140990493, 52.973277963012848 ] } },
{ "type": "Feature", "properties": { "visible_points": 8, "total_points": 56, "visibility_pct": 14.285714285714285 }, "geometry": { "type": "Point", "coordinates": [ -2.159185803707084, 52.973278240160077 ] } },
{ "type": "Feature", "properties": { "visible_points": 4, "total_points": 52, "visibility_pct": 7.6923076923076925 }, "geometry": { "type": "Point", "coordinates": [ -2.158979466420287, 52.973278516949087 ] } },
{ "type": "Feature", "properties": { "visible_points": 4, "total_points": 47, "visibility_pct": 8.5106382978723403 }, "geometry": { "type": "Point", "coordinates": [ -2.158773129130108, 52.973278793379954 ] } },
{ "type": "Feature", "properties": { "visible_points": 0, "total_points": 50, "visibility_pct": 0.0 }, "geometry": { "type": "Point", "coordinates": [ -2.159908383872276, 52.973385141500948 ] } },
{ "type": "Feature", "properties": { "visible_points": 1, "total_points": 56, "visibility_pct": 1.7857142857142856 }, "geometry": { "type": "Point", "coordinates": [ -2.159702046080585, 52.973385419542979 ] } },
{ "type": "Feature", "properties": { "visible_points": 0, "total_points": 56, "visibility_pct": 0.0 }, "geometry": { "type": "Point", "coordinates": [ -2.159495708285501, 52.973385697226831 ] } },
{ "type": "Feature", "properties": { "visible_points": 7, "total_points": 56, "visibility_pct": 12.5 }, "geometry": { "type": "Point", "coordinates": [ -2.159289370487024, 52.973385974552507 ] } },
{ "type": "Feature", "properties": { "visible_points": 5, "total_points": 56, "visibility_pct": 8.9285714285714288 }, "geometry": { "type": "Point", "coordinates": [ -2.159083032685158, 52.973386251520004 ] } },
{ "type": "Feature", "properties": { "visible_points": 0, "total_points": 43, "visibility_pct": 0.0 }, "geometry": { "type": "Point", "coordinates": [ -2.160011952715843, 52.973492875267077 ] } },
{ "type": "Feature", "properties": { "visible_points": 2, "total_points": 50, "visibility_pct": 4.0 }, "geometry": { "type": "Point", "coordinates": [ -2.159805614409093, 52.973493153487581 ] } },
{ "type": "Feature", "properties": { "visible_points": 3, "total_points": 55, "visibility_pct": 5.4545454545454541 }, "geometry": { "type": "Point", "coordinates": [ -2.159599276098945, 52.973493431349901 ] } },
{ "type": "Feature", "properties": { "visible_points": 1, "total_points": 56, "visibility_pct": 1.7857142857142856 }, "geometry": { "type": "Point", "coordinates": [ -2.159392937785402, 52.973493708854072 ] } },
{ "type": "Feature", "properties": { "visible_points": 5, "total_points": 56, "visibility_pct": 8.9285714285714288 }, "geometry": { "type": "Point", "coordinates": [ -2.159186599468473, 52.973493986000044 ] } }
]
}
