{
"type": "FeatureCollection",
"name": "RUGBY_55",
"crs": { "type": "name", "properties": { "name": "urn:ogc:def:crs:OGC:1.3:CRS84" } },
"features": [
{ "type": "Feature", "properties": { "osm_id": 7628140510, "name": null, "amenity": "bench", "man_made": null, "leisure": null, "playground": null, "memorial": null }, "geometry": { "type": "Point", "coordinates": [ -1.238247, 52.3650766 ] } },
{ "type": "Feature", "properties": { "osm_id": 7628140493, "name": null, "amenity": "bench", "man_made": null, "leisure": null, "playground": null, "memorial": null }, "geometry": { "type": "Point", "coordinates": [ -1.2389502, 52.3652268 ] } },
{ "type": "Feature", "properties": { "osm_id": 7628140531, "name": null, "amenity": "bench", "man_made": null, "leisure": null, "playground": null, "memorial": null }, "geometry": { "type": "Point", "coordinates": [ -1.2408853, 52.3655147 ] } },
{ "type": "Feature", "properties": { "osm_id": 7628140489, "name": null, "amenity": "bench", "man_made": null, "leisure": null, "playground": null, "memorial": null }, "geometry": { "type": "Point", "coordinates": [ -1.2408954, 52.3655462 ] } },
{ "type": "Feature", "properties": { "osm_id": 7628133476, "name": null, "amenity": "bench", "man_made": null, "leisure": null, "playground": null, "memorial": null }, "geometry": { "type": "Point", "coordinates": [ -1.2407269, 52.3655469 ] } },
{ "type": "Feature", "properties": { "osm_id": 7628124116, "name": null, "amenity": "bench", "man_made": null, "leisure": null, "playground": null, "memorial": null }, "geometry": { "type": "Point", "coordinates": [ -1.2384957, 52.3659953 ] } }
]
}
