{
"type": "FeatureCollection",
"name": "BIRMI_19_toilets",
"crs": { "type": "name", "properties": { "name": "urn:ogc:def:crs:OGC:1.3:CRS84" } },
"features": [
{ "type": "Feature", "properties": { "name": "Sainsburys", "payment_info": "Cost unknown", "accessible": "True", "radar": "Unknown", "women": "True", "men": "True", "baby_change": "True", "Mon": "09:00-17:00", "Tue": "09:00-17:00", "Wed": "09:00-17:00", "Thu": "09:00-17:00", "Fri": "09:00-17:00", "Sat": "09:00-17:00", "Sun": "09:00-17:00", "index_right": 373, "park_offical_id": "BIRMI_19" }, "geometry": { "type": "Point", "coordinates": [ -1.796708533, 52.517293132 ] } },
{ "type": "Feature", "properties": { "name": "BQ", "payment_info": "Cost unknown", "accessible": "False", "radar": "Unknown", "women": "True", "men": "True", "baby_change": "Unknown", "Mon": "09:00-17:00", "Tue": "09:00-17:00", "Wed": "09:00-17:00", "Thu": "09:00-17:00", "Fri": "09:00-17:00", "Sat": "09:00-17:00", "Sun": "09:00-17:00", "index_right": 373, "park_offical_id": "BIRMI_19" }, "geometry": { "type": "Point", "coordinates": [ -1.800259352, 52.512284854 ] } }
]
}
