{
"type": "FeatureCollection",
"name": "BIRMI_208_toilets",
"crs": { "type": "name", "properties": { "name": "urn:ogc:def:crs:OGC:1.3:CRS84" } },
"features": [
{ "type": "Feature", "properties": { "name": "Asda", "payment_info": "Free", "accessible": "True", "radar": "True", "women": "True", "men": "True", "baby_change": "True", "Mon": "06:00-00:00", "Tue": "06:00-00:00", "Wed": "06:00-00:00", "Thu": "06:00-00:00", "Fri": "06:00-00:00", "Sat": "06:00-00:00", "Sun": "11:00-17:00", "index_right": 415, "park_offical_id": "BIRMI_208" }, "geometry": { "type": "Point", "coordinates": [ -1.84243083, 52.464246294 ] } }
]
}
