{
"type": "FeatureCollection",
"name": "BIRMI_134_toilets",
"crs": { "type": "name", "properties": { "name": "urn:ogc:def:crs:OGC:1.3:CRS84" } },
"features": [
{ "type": "Feature", "properties": { "name": "Coach station", "payment_info": "30p", "accessible": "False", "radar": "Unknown", "women": "True", "men": "True", "baby_change": "Unknown", "Mon": "00:00-00:00", "Tue": "00:00-00:00", "Wed": "00:00-00:00", "Thu": "00:00-00:00", "Fri": "00:00-00:00", "Sat": "00:00-00:00", "Sun": "00:00-00:00", "index_right": 147, "park_offical_id": "BIRMI_134" }, "geometry": { "type": "Point", "coordinates": [ -1.8882313, 52.4751343 ] } }
]
}
