{
"type": "FeatureCollection",
"name": "BIRMI_63_toilets",
"crs": { "type": "name", "properties": { "name": "urn:ogc:def:crs:OGC:1.3:CRS84" } },
"features": [
{ "type": "Feature", "properties": { "name": "Sainsburys", "payment_info": "Free", "accessible": "True", "radar": "False", "women": "True", "men": "True", "baby_change": "True", "Mon": "07:00-22:00", "Tue": "07:00-22:00", "Wed": "07:00-22:00", "Thu": "07:00-22:00", "Fri": "07:00-22:00", "Sat": "07:00-22:00", "Sun": "08:00-17:00", "index_right": 807, "park_offical_id": "BIRMI_63" }, "geometry": { "type": "Point", "coordinates": [ -1.982898116, 52.396162788 ] } },
{ "type": "Feature", "properties": { "name": "Longbridge Station", "payment_info": "Free", "accessible": "True", "radar": "True", "women": "True", "men": "True", "baby_change": "False", "Mon": "06:00-20:00", "Tue": "06:00-20:00", "Wed": "06:00-20:00", "Thu": "06:00-20:00", "Fri": "06:00-20:00", "Sat": "07:00-20:00", "Sun": "09:30-15:00", "index_right": 807, "park_offical_id": "BIRMI_63" }, "geometry": { "type": "Point", "coordinates": [ -1.981291124, 52.39642483 ] } }
]
}
