{
"type": "FeatureCollection",
"name": "BIRMI_239_toilets",
"crs": { "type": "name", "properties": { "name": "urn:ogc:def:crs:OGC:1.3:CRS84" } },
"features": [
{ "type": "Feature", "properties": { "name": "Tesco", "payment_info": "Free", "accessible": "False", "radar": "Unknown", "women": "True", "men": "True", "baby_change": "Unknown", "Mon": "Unknown", "Tue": "Unknown", "Wed": "Unknown", "Thu": "Unknown", "Fri": "Unknown", "Sat": "Unknown", "Sun": "Unknown", "index_right": 494, "park_offical_id": "BIRMI_239" }, "geometry": { "type": "Point", "coordinates": [ -1.818294525, 52.49442093 ] } }
]
}
