{
"type": "FeatureCollection",
"name": "STAMO_31_toilets",
"crs": { "type": "name", "properties": { "name": "urn:ogc:def:crs:OGC:1.3:CRS84" } },
"features": [
{ "type": "Feature", "properties": { "name": "Morrisons", "payment_info": "Free", "accessible": "Unknown", "radar": "Unknown", "women": "Unknown", "men": "Unknown", "baby_change": "Unknown", "Mon": "Unknown", "Tue": "Unknown", "Wed": "Unknown", "Thu": "Unknown", "Fri": "Unknown", "Sat": "Unknown", "Sun": "Unknown", "index_right": 27, "park_offical_id": "STAMO_31" }, "geometry": { "type": "Point", "coordinates": [ -2.032159567, 53.100006104 ] } },
{ "type": "Feature", "properties": { "name": "Public Toilets", "payment_info": "Free", "accessible": "Unknown", "radar": "Unknown", "women": "Unknown", "men": "Unknown", "baby_change": "Unknown", "Mon": "Unknown", "Tue": "Unknown", "Wed": "Unknown", "Thu": "Unknown", "Fri": "Unknown", "Sat": "Unknown", "Sun": "Unknown", "index_right": 27, "park_offical_id": "STAMO_31" }, "geometry": { "type": "Point", "coordinates": [ -2.023793936, 53.106376648 ] } },
{ "type": "Feature", "properties": { "name": "Silk Streetentrance to car park", "payment_info": "Free", "accessible": "True", "radar": "False", "women": "True", "men": "True", "baby_change": "True", "Mon": "08:00-18:00", "Tue": "08:00-18:00", "Wed": "08:00-18:00", "Thu": "08:00-18:00", "Fri": "08:00-18:00", "Sat": "08:00-18:00", "Sun": "08:00-18:00", "index_right": 27, "park_offical_id": "STAMO_31" }, "geometry": { "type": "Point", "coordinates": [ -2.023766935, 53.10631176 ] } }
]
}
