{
"type": "FeatureCollection",
"name": "REDDI_18_toilets",
"crs": { "type": "name", "properties": { "name": "urn:ogc:def:crs:OGC:1.3:CRS84" } },
"features": [
{ "type": "Feature", "properties": { "name": "Sainsburys Redditch", "payment_info": "Cost unknown", "accessible": "True", "radar": "Unknown", "women": "Unknown", "men": "Unknown", "baby_change": "True", "Mon": "Unknown", "Tue": "Unknown", "Wed": "Unknown", "Thu": "Unknown", "Fri": "Unknown", "Sat": "Unknown", "Sun": "Unknown", "index_right": 10, "park_offical_id": "REDDI_18" }, "geometry": { "type": "Point", "coordinates": [ -1.939082275, 52.313029 ] } }
]
}
