{
"type": "FeatureCollection",
"name": "DUDLE_482_toilets",
"crs": { "type": "name", "properties": { "name": "urn:ogc:def:crs:OGC:1.3:CRS84" } },
"features": [
{ "type": "Feature", "properties": { "name": "Castleton Street", "payment_info": "Free", "accessible": "False", "radar": "Unknown", "women": "True", "men": "True", "baby_change": "True", "Mon": "07:00-15:30", "Tue": "07:00-15:30", "Wed": "07:00-15:30", "Thu": "07:00-15:30", "Fri": "07:00-15:30", "Sat": "07:00-15:30", "Sun": "Closed", "index_right": 154, "park_offical_id": "DUDLE_482" }, "geometry": { "type": "Point", "coordinates": [ -2.083722353, 52.490574426 ] } }
]
}
