{
"type": "FeatureCollection",
"name": "NEWCA_35",
"crs": { "type": "name", "properties": { "name": "urn:ogc:def:crs:OGC:1.3:CRS84" } },
"features": [
{ "type": "Feature", "properties": { "osm_id": 12090452736, "name": null, "amenity": "bench", "man_made": null, "leisure": null, "playground": null, "memorial": null }, "geometry": { "type": "Point", "coordinates": [ -2.2204148, 53.0163487 ] } },
{ "type": "Feature", "properties": { "osm_id": 12090452576, "name": null, "amenity": "bench", "man_made": null, "leisure": null, "playground": null, "memorial": null }, "geometry": { "type": "Point", "coordinates": [ -2.2196608, 53.0165208 ] } },
{ "type": "Feature", "properties": { "osm_id": 12090455227, "name": null, "amenity": "bench", "man_made": null, "leisure": null, "playground": null, "memorial": null }, "geometry": { "type": "Point", "coordinates": [ -2.2202725, 53.0166069 ] } }
]
}
