{
"type": "FeatureCollection",
"name": "NEWCA_56",
"crs": { "type": "name", "properties": { "name": "urn:ogc:def:crs:OGC:1.3:CRS84" } },
"features": [
{ "type": "Feature", "properties": { "osm_id": 4393995348, "name": null, "amenity": "bench", "man_made": null, "leisure": null, "playground": null, "memorial": null }, "geometry": { "type": "Point", "coordinates": [ -2.2403931, 53.0176606 ] } },
{ "type": "Feature", "properties": { "osm_id": 4393995352, "name": null, "amenity": "bench", "man_made": null, "leisure": null, "playground": null, "memorial": null }, "geometry": { "type": "Point", "coordinates": [ -2.2415106, 53.0192651 ] } },
{ "type": "Feature", "properties": { "osm_id": 4393995354, "name": null, "amenity": "bench", "man_made": null, "leisure": null, "playground": null, "memorial": null }, "geometry": { "type": "Point", "coordinates": [ -2.2420917, 53.0196075 ] } },
{ "type": "Feature", "properties": { "osm_id": 4393995345, "name": null, "amenity": "bench", "man_made": null, "leisure": null, "playground": null, "memorial": null }, "geometry": { "type": "Point", "coordinates": [ -2.2427027, 53.0199805 ] } },
{ "type": "Feature", "properties": { "osm_id": 4393995340, "name": null, "amenity": "bench", "man_made": null, "leisure": null, "playground": null, "memorial": null }, "geometry": { "type": "Point", "coordinates": [ -2.2432182, 53.0203103 ] } }
]
}
