{
"type": "FeatureCollection",
"name": "WARWI_171",
"crs": { "type": "name", "properties": { "name": "urn:ogc:def:crs:OGC:1.3:CRS84" } },
"features": [
{ "type": "Feature", "properties": { "osm_id": 7882205714, "name": null, "amenity": "bench", "man_made": null, "leisure": null, "playground": null, "memorial": null }, "geometry": { "type": "Point", "coordinates": [ -1.5194026, 52.273432 ] } },
{ "type": "Feature", "properties": { "osm_id": 7942810774, "name": null, "amenity": "bench", "man_made": null, "leisure": null, "playground": null, "memorial": null }, "geometry": { "type": "Point", "coordinates": [ -1.5191066, 52.2734636 ] } },
{ "type": "Feature", "properties": { "osm_id": 7882205713, "name": null, "amenity": "bench", "man_made": null, "leisure": null, "playground": null, "memorial": null }, "geometry": { "type": "Point", "coordinates": [ -1.5197808, 52.2735215 ] } },
{ "type": "Feature", "properties": { "osm_id": 7882205715, "name": null, "amenity": "bench", "man_made": null, "leisure": null, "playground": null, "memorial": null }, "geometry": { "type": "Point", "coordinates": [ -1.5193905, 52.2735625 ] } },
{ "type": "Feature", "properties": { "osm_id": 7882205712, "name": null, "amenity": "bench", "man_made": null, "leisure": null, "playground": null, "memorial": null }, "geometry": { "type": "Point", "coordinates": [ -1.5197634, 52.2736872 ] } }
]
}
