{
"type": "FeatureCollection",
"name": "WARWI_55",
"crs": { "type": "name", "properties": { "name": "urn:ogc:def:crs:OGC:1.3:CRS84" } },
"features": [
{ "type": "Feature", "properties": { "osm_id": 8039971602, "name": null, "amenity": null, "man_made": null, "leisure": "picnic_table", "playground": null, "memorial": null }, "geometry": { "type": "Point", "coordinates": [ -1.542071, 52.294367 ] } },
{ "type": "Feature", "properties": { "osm_id": 8039971606, "name": null, "amenity": "bench", "man_made": null, "leisure": null, "playground": null, "memorial": null }, "geometry": { "type": "Point", "coordinates": [ -1.5421855, 52.2944227 ] } },
{ "type": "Feature", "properties": { "osm_id": 8039971600, "name": null, "amenity": "bench", "man_made": null, "leisure": null, "playground": null, "memorial": null }, "geometry": { "type": "Point", "coordinates": [ -1.5428111, 52.2947201 ] } }
]
}
