{
"type": "FeatureCollection",
"name": "WARWI_101",
"crs": { "type": "name", "properties": { "name": "urn:ogc:def:crs:OGC:1.3:CRS84" } },
"features": [
{ "type": "Feature", "properties": { "osm_id": 8995825621, "name": null, "amenity": "bench", "man_made": null, "leisure": null, "playground": null, "memorial": null }, "geometry": { "type": "Point", "coordinates": [ -1.5444979, 52.2818687 ] } },
{ "type": "Feature", "properties": { "osm_id": 8995825622, "name": null, "amenity": "bench", "man_made": null, "leisure": null, "playground": null, "memorial": null }, "geometry": { "type": "Point", "coordinates": [ -1.5446295, 52.2819708 ] } },
{ "type": "Feature", "properties": { "osm_id": 8995825623, "name": null, "amenity": "bench", "man_made": null, "leisure": null, "playground": null, "memorial": null }, "geometry": { "type": "Point", "coordinates": [ -1.5449273, 52.2820074 ] } },
{ "type": "Feature", "properties": { "osm_id": 9757485812, "name": null, "amenity": "bench", "man_made": null, "leisure": null, "playground": null, "memorial": null }, "geometry": { "type": "Point", "coordinates": [ -1.5465694, 52.2821872 ] } },
{ "type": "Feature", "properties": { "osm_id": 9757485814, "name": null, "amenity": "bench", "man_made": null, "leisure": null, "playground": null, "memorial": null }, "geometry": { "type": "Point", "coordinates": [ -1.546099, 52.2823418 ] } },
{ "type": "Feature", "properties": { "osm_id": 8995825641, "name": null, "amenity": "bench", "man_made": null, "leisure": null, "playground": null, "memorial": null }, "geometry": { "type": "Point", "coordinates": [ -1.5453613, 52.2824017 ] } },
{ "type": "Feature", "properties": { "osm_id": 9757485813, "name": null, "amenity": "bench", "man_made": null, "leisure": null, "playground": null, "memorial": null }, "geometry": { "type": "Point", "coordinates": [ -1.5457114, 52.2824638 ] } }
]
}
